[
  {
    "link_it": "https://github.com/lmbstudiocontact/cb_img_2500_it_2/raw/main/spoon_cb_img_2500_it.json",
    "id_item": "spoon_cb_img_2500_it",
    "id_album": "1958080175",
    "english": "spoon",
    "list_mean": [
      "cái thìa",
      "lượng mà thìa có thể đựng",
      "dùng thìa múc cái gì lên"
    ],
    "cau_en": "",
    "cau_vn": "",
    "hash_code_list_mean": "1006136238",
    "list_img": [
      {
        "link_thumb": "https://live.staticflickr.com/65535/51809467598_47c0d1a09d_n.jpg",
        "link_img": "https://live.staticflickr.com/65535/51809467598_d0c2305058_o.png",
        "id_image": "spoon_263740"
      },
      {
        "link_thumb": "https://live.staticflickr.com/65535/51808397702_75613bacd6_n.jpg",
        "link_img": "https://live.staticflickr.com/65535/51808397702_51a656b9c4_o.png",
        "id_image": "spoon_265400"
      }
    ],
    "hash_code_list_img": "-776149683"
  },
  {
    "link_it": "https://github.com/lmbstudiocontact/cb_img_2500_it_2/raw/main/stick_cb_img_2500_it.json",
    "id_item": "stick_cb_img_2500_it",
    "id_album": "1958080175",
    "english": "stick",
    "list_mean": [
      "đâm, thọc, chọc",
      "cắm",
      "dán, dính",
      "làm sa lầy, làm vướng mắc",
      "que củi",
      "cái gậy",
      "cán"
    ],
    "cau_en": "",
    "cau_vn": "",
    "hash_code_list_mean": "-753306758",
    "list_img": [
      {
        "link_thumb": "https://live.staticflickr.com/65535/51810084170_00bbfc2000_n.jpg",
        "link_img": "https://live.staticflickr.com/65535/51810084170_2aff594df3_o.png",
        "id_image": "stick_3441385"
      },
      {
        "link_thumb": "https://live.staticflickr.com/65535/51810084200_e5ab064369_n.jpg",
        "link_img": "https://live.staticflickr.com/65535/51810084200_08c6f3f7e6_o.png",
        "id_image": "stick_939445"
      }
    ],
    "hash_code_list_img": "-1181395950"
  },
  {
    "link_it": "https://github.com/lmbstudiocontact/cb_img_2500_it_2/raw/main/worker_cb_img_2500_it.json",
    "id_item": "worker_cb_img_2500_it",
    "id_album": "1958080175",
    "english": "worker",
    "list_mean": [
      "công nhân",
      "thường là công nhân làm việc chân tay",
      "người lao động"
    ],
    "cau_en": "",
    "cau_vn": "",
    "hash_code_list_mean": "-1507047102",
    "list_img": [
      {
        "link_thumb": "https://live.staticflickr.com/65535/51809689359_22ae561cc3_n.jpg",
        "link_img": "https://live.staticflickr.com/65535/51809689359_0051beb1b9_o.png",
        "id_image": "worker_313100"
      },
      {
        "link_thumb": "https://live.staticflickr.com/65535/51809449283_590f855111_n.jpg",
        "link_img": "https://live.staticflickr.com/65535/51809449283_20f111f03f_o.png",
        "id_image": "worker_562536"
      }
    ],
    "hash_code_list_img": "-729311658"
  },
  {
    "link_it": "https://github.com/lmbstudiocontact/cb_img_2500_it_2/raw/main/research_cb_img_2500_it.json",
    "id_item": "research_cb_img_2500_it",
    "id_album": "1958080175",
    "english": "research",
    "list_mean": [
      "cuộc nghiên cứu",
      "nghiên cứu"
    ],
    "cau_en": "",
    "cau_vn": "",
    "hash_code_list_mean": "1076221917",
    "list_img": [
      {
        "link_thumb": "https://live.staticflickr.com/65535/51810058965_bc6ab21ba4_n.jpg",
        "link_img": "https://live.staticflickr.com/65535/51810058965_9fb76804c6_o.png",
        "id_image": "research_1032124"
      },
      {
        "link_thumb": "https://live.staticflickr.com/65535/51809437383_8914f3fe7b_n.jpg",
        "link_img": "https://live.staticflickr.com/65535/51809437383_3fa00531a8_o.png",
        "id_image": "research_1671644"
      },
      {
        "link_thumb": "https://live.staticflickr.com/65535/51810058970_202ee9321f_n.jpg",
        "link_img": "https://live.staticflickr.com/65535/51810058970_3cd90b83a7_o.png",
        "id_image": "research_901046"
      }
    ],
    "hash_code_list_img": "-936852474"
  },
  {
    "link_it": "https://github.com/lmbstudiocontact/cb_img_2500_it_0/raw/main/concept_cb_img_2500_it.json",
    "id_item": "concept_cb_img_2500_it",
    "id_album": "1958080175",
    "english": "concept",
    "list_mean": [
      "khái niệm"
    ],
    "cau_en": "",
    "cau_vn": "",
    "hash_code_list_mean": "1603650331",
    "list_img": [
      {
        "link_thumb": "https://live.staticflickr.com/65535/51810050565_ebfc2895bc_n.jpg",
        "link_img": "https://live.staticflickr.com/65535/51810050565_a07e04a32b_o.png",
        "id_image": "concept_2111175"
      },
      {
        "link_thumb": "https://live.staticflickr.com/65535/51809668664_18757759df_n.jpg",
        "link_img": "https://live.staticflickr.com/65535/51809668664_ca08e93ffd_o.png",
        "id_image": "concept_2311639"
      },
      {
        "link_thumb": "https://live.staticflickr.com/65535/51809428758_3cb2793963_n.jpg",
        "link_img": "https://live.staticflickr.com/65535/51809428758_bb3cddf717_o.png",
        "id_image": "concept_4234369"
      }
    ],
    "hash_code_list_img": "-1047198950"
  },
  {
    "link_it": "https://github.com/lmbstudiocontact/cb_img_2500_it_1/raw/main/liver_cb_img_2500_it.json",
    "id_item": "liver_cb_img_2500_it",
    "id_album": "1958080175",
    "english": "liver",
    "list_mean": [
      "gan",
      "bộ gan"
    ],
    "cau_en": "",
    "cau_vn": "",
    "hash_code_list_mean": "1512989016",
    "list_img": [
      {
        "link_thumb": "https://live.staticflickr.com/65535/51809339271_f5b8156495_n.jpg",
        "link_img": "https://live.staticflickr.com/65535/51809339271_b08efdcebb_o.png",
        "id_image": "liver_245278"
      },
      {
        "link_thumb": "https://live.staticflickr.com/65535/51809694354_ab8831bb44_n.jpg",
        "link_img": "https://live.staticflickr.com/65535/51809694354_2f8fa42ca2_o.png",
        "id_image": "liver_6147604"
      },
      {
        "link_thumb": "https://live.staticflickr.com/65535/51808384142_3b57c54b71_n.jpg",
        "link_img": "https://live.staticflickr.com/65535/51808384142_9202f3c894_o.png",
        "id_image": "liver_6350266"
      }
    ],
    "hash_code_list_img": "228386226"
  },
  {
    "link_it": "https://github.com/lmbstudiocontact/cb_img_2500_it_2/raw/main/shallow_cb_img_2500_it.json",
    "id_item": "shallow_cb_img_2500_it",
    "id_album": "1958080175",
    "english": "shallow",
    "list_mean": [
      "nông, cạn",
      "nông cạn , hời hợt"
    ],
    "cau_en": "",
    "cau_vn": "",
    "hash_code_list_mean": "938425932",
    "list_img": [
      {
        "link_thumb": "https://live.staticflickr.com/65535/51808392422_d5dc7f4c58_n.jpg",
        "link_img": "https://live.staticflickr.com/65535/51808392422_24ee753da5_o.png",
        "id_image": "shallow_4745395"
      }
    ],
    "hash_code_list_img": "995621172"
  },
  {
    "link_it": "https://github.com/lmbstudiocontact/cb_img_2500_it_2/raw/main/rinse_cb_img_2500_it.json",
    "id_item": "rinse_cb_img_2500_it",
    "id_album": "1958080175",
    "english": "rinse",
    "list_mean": [
      "giặt",
      "súc; rửa",
      "sự súc rửa",
      "thuốc nhuộm tóc"
    ],
    "cau_en": "",
    "cau_vn": "",
    "hash_code_list_mean": "1293847885",
    "list_img": [
      {
        "link_thumb": "https://live.staticflickr.com/65535/51808391092_78299711d2_n.jpg",
        "link_img": "https://live.staticflickr.com/65535/51808391092_b789ea5763_o.png",
        "id_image": "rinse_1415738"
      },
      {
        "link_thumb": "https://live.staticflickr.com/65535/51810083520_c16ae1c5ff_n.jpg",
        "link_img": "https://live.staticflickr.com/65535/51810083520_0c434e17e9_o.png",
        "id_image": "rinse_2654602"
      },
      {
        "link_thumb": "https://live.staticflickr.com/65535/51809460808_24b15537b9_n.jpg",
        "link_img": "https://live.staticflickr.com/65535/51809460808_7fe8b024c4_o.png",
        "id_image": "rinse_2780619"
      },
      {
        "link_thumb": "https://live.staticflickr.com/65535/51809346136_566b4059d2_n.jpg",
        "link_img": "https://live.staticflickr.com/65535/51809346136_00c3bbc148_o.png",
        "id_image": "rinse_525824"
      }
    ],
    "hash_code_list_img": "1612516578"
  },
  {
    "link_it": "https://github.com/lmbstudiocontact/cb_img_2500_it_0/raw/main/duct_cb_img_2500_it.json",
    "id_item": "duct_cb_img_2500_it",
    "id_album": "1958080175",
    "english": "duct",
    "list_mean": [
      "ống dẫn"
    ],
    "cau_en": "",
    "cau_vn": "",
    "hash_code_list_mean": "-329498160",
    "list_img": [
      {
        "link_thumb": "https://live.staticflickr.com/65535/51808380677_03bcf18a48_n.jpg",
        "link_img": "https://live.staticflickr.com/65535/51808380677_05ffb72c7a_o.png",
        "id_image": "duct_4752685"
      }
    ],
    "hash_code_list_img": "109978886"
  },
  {
    "link_it": "https://github.com/lmbstudiocontact/cb_img_2500_it_2/raw/main/saline_cb_img_2500_it.json",
    "id_item": "saline_cb_img_2500_it",
    "id_album": "1958080175",
    "english": "saline",
    "list_mean": [
      "có muối"
    ],
    "cau_en": "",
    "cau_vn": "",
    "hash_code_list_mean": "363624623",
    "list_img": [
      {
        "link_thumb": "https://live.staticflickr.com/65535/51810073335_a7a4766e1e_n.jpg",
        "link_img": "https://live.staticflickr.com/65535/51810073335_cf15760820_o.png",
        "id_image": "saline_2941513"
      },
      {
        "link_thumb": "https://live.staticflickr.com/65535/51809691714_9797c0998e_n.jpg",
        "link_img": "https://live.staticflickr.com/65535/51809691714_56da76f613_o.png",
        "id_image": "saline_469426"
      },
      {
        "link_thumb": "https://live.staticflickr.com/65535/51810073375_66657408ab_n.jpg",
        "link_img": "https://live.staticflickr.com/65535/51810073375_3606c121fb_o.png",
        "id_image": "saline_813604"
      }
    ],
    "hash_code_list_img": "-30845245"
  },
  {
    "link_it": "https://github.com/lmbstudiocontact/cb_img_2500_it_2/raw/main/triumph_cb_img_2500_it.json",
    "id_item": "triumph_cb_img_2500_it",
    "id_album": "1958080175",
    "english": "triumph",
    "list_mean": [
      "chiến thắng",
      "hạnh phúc, niềm vui chiến thắng",
      "chiến thắng"
    ],
    "cau_en": "",
    "cau_vn": "",
    "hash_code_list_mean": "-755417997",
    "list_img": [
      {
        "link_thumb": "https://live.staticflickr.com/65535/51809448018_9ff993c6d2_n.jpg",
        "link_img": "https://live.staticflickr.com/65535/51809448018_d5169374c6_o.png",
        "id_image": "triumph_1805251"
      },
      {
        "link_thumb": "https://live.staticflickr.com/65535/51810069770_0037b9ac62_n.jpg",
        "link_img": "https://live.staticflickr.com/65535/51810069770_03229b74f9_o.png",
        "id_image": "triumph_1961433"
      },
      {
        "link_thumb": "https://live.staticflickr.com/65535/51808377842_e474184aff_n.jpg",
        "link_img": "https://live.staticflickr.com/65535/51808377842_117277258a_o.png",
        "id_image": "triumph_708665"
      }
    ],
    "hash_code_list_img": "-998689334"
  },
  {
    "link_it": "https://github.com/lmbstudiocontact/cb_img_2500_it_0/raw/main/develop_cb_img_2500_it.json",
    "id_item": "develop_cb_img_2500_it",
    "id_album": "1958080175",
    "english": "develop",
    "list_mean": [
      "mở rộng",
      "phát triển",
      "bộc lộ rõ",
      "rửa ảnh"
    ],
    "cau_en": "",
    "cau_vn": "",
    "hash_code_list_mean": "-1296499371",
    "list_img": [
      {
        "link_thumb": "https://live.staticflickr.com/65535/51809681239_770d5a38a4_n.jpg",
        "link_img": "https://live.staticflickr.com/65535/51809681239_f02ae56f22_o.png",
        "id_image": "develop_2419250"
      },
      {
        "link_thumb": "https://live.staticflickr.com/65535/51810062915_be749ea41a_n.jpg",
        "link_img": "https://live.staticflickr.com/65535/51810062915_9b1125d2bb_o.png",
        "id_image": "develop_2503624"
      },
      {
        "link_thumb": "https://live.staticflickr.com/65535/51809326081_414fa8bae0_n.jpg",
        "link_img": "https://live.staticflickr.com/65535/51809326081_70239d863f_o.png",
        "id_image": "develop_2535486"
      },
      {
        "link_thumb": "https://live.staticflickr.com/65535/51809681309_e5f9737632_n.jpg",
        "link_img": "https://live.staticflickr.com/65535/51809681309_5ce137b44e_o.png",
        "id_image": "develop_421694"
      },
      {
        "link_thumb": "https://live.staticflickr.com/65535/51809441173_8dba9e7066_n.jpg",
        "link_img": "https://live.staticflickr.com/65535/51809441173_73a6da50e8_o.png",
        "id_image": "develop_943797"
      }
    ],
    "hash_code_list_img": "-1471148566"
  },
  {
    "link_it": "https://github.com/lmbstudiocontact/cb_img_2500_it_2/raw/main/wrench_cb_img_2500_it.json",
    "id_item": "wrench_cb_img_2500_it",
    "id_album": "1958080175",
    "english": "wrench",
    "list_mean": [
      "giật mạnh",
      "trật khớp",
      "sự giật mạnh",
      "chìa vặn"
    ],
    "cau_en": "",
    "cau_vn": "",
    "hash_code_list_mean": "-851929939",
    "list_img": [
      {
        "link_thumb": "https://live.staticflickr.com/65535/51808377612_29ffa0bf71_n.jpg",
        "link_img": "https://live.staticflickr.com/65535/51808377612_310364248e_o.png",
        "id_image": "wrench_1768196"
      },
      {
        "link_thumb": "https://live.staticflickr.com/65535/51809447813_d40b5ff458_n.jpg",
        "link_img": "https://live.staticflickr.com/65535/51809447813_0826f5412e_o.png",
        "id_image": "wrench_2137963"
      }
    ],
    "hash_code_list_img": "1298480397"
  },
  {
    "link_it": "https://github.com/lmbstudiocontact/cb_img_2500_it_0/raw/main/beggar_cb_img_2500_it.json",
    "id_item": "beggar_cb_img_2500_it",
    "id_album": "1958080175",
    "english": "beggar",
    "list_mean": [
      "nguời ăn xin",
      "làm nghèo đi"
    ],
    "cau_en": "",
    "cau_vn": "",
    "hash_code_list_mean": "-344046230",
    "list_img": [
      {
        "link_thumb": "https://live.staticflickr.com/65535/51809423968_0349fd72b5_n.jpg",
        "link_img": "https://live.staticflickr.com/65535/51809423968_4a7f0e7e85_o.png",
        "id_image": "beggar_4244635"
      },
      {
        "link_thumb": "https://live.staticflickr.com/65535/51810045715_56858ea5d9_n.jpg",
        "link_img": "https://live.staticflickr.com/65535/51810045715_1ba689ecdc_o.png",
        "id_image": "beggar_4244641"
      },
      {
        "link_thumb": "https://live.staticflickr.com/65535/51808352902_3351a5137a_n.jpg",
        "link_img": "https://live.staticflickr.com/65535/51808352902_b35d4a4ed3_o.png",
        "id_image": "beggar_5256187"
      },
      {
        "link_thumb": "https://live.staticflickr.com/65535/51809664034_6a9b7a6831_n.jpg",
        "link_img": "https://live.staticflickr.com/65535/51809664034_554fa23ea3_o.png",
        "id_image": "beggar_949555"
      }
    ],
    "hash_code_list_img": "1045720301"
  },
  {
    "link_it": "https://github.com/lmbstudiocontact/cb_img_2500_it_0/raw/main/channel_cb_img_2500_it.json",
    "id_item": "channel_cb_img_2500_it",
    "id_album": "1958080175",
    "english": "channel",
    "list_mean": [
      "rãnh",
      "luồng",
      "eo biển",
      "kênh",
      "kênh",
      "đào rãnh",
      "hướng vào"
    ],
    "cau_en": "",
    "cau_vn": "",
    "hash_code_list_mean": "1602201301",
    "list_img": [
      {
        "link_thumb": "https://live.staticflickr.com/65535/51809429058_71ecf13d8d_n.jpg",
        "link_img": "https://live.staticflickr.com/65535/51809429058_bff66bfe50_o.png",
        "id_image": "channel_1207578"
      },
      {
        "link_thumb": "https://live.staticflickr.com/65535/51809314116_ddc5119297_n.jpg",
        "link_img": "https://live.staticflickr.com/65535/51809314116_739a763f05_o.png",
        "id_image": "channel_4062101"
      },
      {
        "link_thumb": "https://live.staticflickr.com/65535/51808358307_7d991f8e2d_n.jpg",
        "link_img": "https://live.staticflickr.com/65535/51808358307_fc6e2702d2_o.png",
        "id_image": "channel_4577178"
      },
      {
        "link_thumb": "https://live.staticflickr.com/65535/51809314036_3965b4e757_n.jpg",
        "link_img": "https://live.staticflickr.com/65535/51809314036_ffe06cd301_o.png",
        "id_image": "channel_5853646"
      },
      {
        "link_thumb": "https://live.staticflickr.com/65535/51810050830_2716e78a7d_n.jpg",
        "link_img": "https://live.staticflickr.com/65535/51810050830_9f5d9f0f6a_o.png",
        "id_image": "channel_650975"
      }
    ],
    "hash_code_list_img": "-622355073"
  },
  {
    "link_it": "https://github.com/lmbstudiocontact/cb_img_2500_it_1/raw/main/outside_cb_img_2500_it.json",
    "id_item": "outside_cb_img_2500_it",
    "id_album": "1958080175",
    "english": "outside",
    "list_mean": [
      "bề ngoài",
      "phía ngoài",
      "từ bên ngoài",
      "mỏng manh",
      "bên ngoài",
      "bề ngoài",
      "ngoài"
    ],
    "cau_en": "",
    "cau_vn": "",
    "hash_code_list_mean": "896814785",
    "list_img": [
      {
        "link_thumb": "https://live.staticflickr.com/65535/51809341251_fa8d462072_n.jpg",
        "link_img": "https://live.staticflickr.com/65535/51809341251_1d22a81f3a_o.png",
        "id_image": "outside_1827229"
      },
      {
        "link_thumb": "https://live.staticflickr.com/65535/51809696459_72077806c6_n.jpg",
        "link_img": "https://live.staticflickr.com/65535/51809696459_9ab1672208_o.png",
        "id_image": "outside_1828569"
      },
      {
        "link_thumb": "https://live.staticflickr.com/65535/51808386187_391e00844f_n.jpg",
        "link_img": "https://live.staticflickr.com/65535/51808386187_ba0a99d76a_o.png",
        "id_image": "outside_5029613"
      }
    ],
    "hash_code_list_img": "-1082055662"
  },
  {
    "link_it": "https://github.com/lmbstudiocontact/cb_img_2500_it_1/raw/main/plastic_cb_img_2500_it.json",
    "id_item": "plastic_cb_img_2500_it",
    "id_album": "1958080175",
    "english": "plastic",
    "list_mean": [
      "chất dẻo",
      "dễ tạo hình"
    ],
    "cau_en": "",
    "cau_vn": "",
    "hash_code_list_mean": "-1066716688",
    "list_img": [
      {
        "link_thumb": "https://live.staticflickr.com/65535/51809342066_18250c2760_n.jpg",
        "link_img": "https://live.staticflickr.com/65535/51809342066_062e4641dd_o.png",
        "id_image": "plastic_1889993"
      },
      {
        "link_thumb": "https://live.staticflickr.com/65535/51810079400_3aaa371727_n.jpg",
        "link_img": "https://live.staticflickr.com/65535/51810079400_20f1884b92_o.png",
        "id_image": "plastic_1996983"
      },
      {
        "link_thumb": "https://live.staticflickr.com/65535/51810079380_904cc34e85_n.jpg",
        "link_img": "https://live.staticflickr.com/65535/51810079380_d6e7475105_o.png",
        "id_image": "plastic_4201885"
      }
    ],
    "hash_code_list_img": "-1074369024"
  },
  {
    "link_it": "https://github.com/lmbstudiocontact/cb_img_2500_it_1/raw/main/grinder_cb_img_2500_it.json",
    "id_item": "grinder_cb_img_2500_it",
    "id_album": "1958080175",
    "english": "grinder",
    "list_mean": [
      "cối xay, máy nghiền"
    ],
    "cau_en": "",
    "cau_vn": "",
    "hash_code_list_mean": "-1903539232",
    "list_img": [
      {
        "link_thumb": "https://live.staticflickr.com/65535/51808366207_a1664847a0_n.jpg",
        "link_img": "https://live.staticflickr.com/65535/51808366207_9a979eae56_o.png",
        "id_image": "grinder_1111097"
      },
      {
        "link_thumb": "https://live.staticflickr.com/65535/51809436523_01aa5a3593_n.jpg",
        "link_img": "https://live.staticflickr.com/65535/51809436523_ca95f03d4f_o.png",
        "id_image": "grinder_2670368"
      },
      {
        "link_thumb": "https://live.staticflickr.com/65535/51810057960_fa0e2f830a_n.jpg",
        "link_img": "https://live.staticflickr.com/65535/51810057960_faa328fa63_o.png",
        "id_image": "grinder_5181748"
      },
      {
        "link_thumb": "https://live.staticflickr.com/65535/51809436598_66e0f5b4da_n.jpg",
        "link_img": "https://live.staticflickr.com/65535/51809436598_8c1128929c_o.png",
        "id_image": "grinder_808746"
      }
    ],
    "hash_code_list_img": "541373631"
  },
  {
    "link_it": "https://github.com/lmbstudiocontact/cb_img_2500_it_2/raw/main/understand_cb_img_2500_it.json",
    "id_item": "understand_cb_img_2500_it",
    "id_album": "1958080175",
    "english": "understand",
    "list_mean": [
      "hiểu được ý",
      "hiểu, nhận thức được",
      "hiểu, nhận ra"
    ],
    "cau_en": "",
    "cau_vn": "",
    "hash_code_list_mean": "-947911902",
    "list_img": [
      {
        "link_thumb": "https://live.staticflickr.com/65535/51808398667_bf61266c29_n.jpg",
        "link_img": "https://live.staticflickr.com/65535/51808398667_3a7e3b51c5_o.png",
        "id_image": "understand_2196303"
      },
      {
        "link_thumb": "https://live.staticflickr.com/65535/51809353691_4f70ed0429_n.jpg",
        "link_img": "https://live.staticflickr.com/65535/51809353691_5657b51fc1_o.png",
        "id_image": "understand_5361244"
      },
      {
        "link_thumb": "https://live.staticflickr.com/65535/51808398632_6f84fb2977_n.jpg",
        "link_img": "https://live.staticflickr.com/65535/51808398632_f703396747_o.png",
        "id_image": "understand_6159589"
      }
    ],
    "hash_code_list_img": "-1887418167"
  },
  {
    "link_it": "https://github.com/lmbstudiocontact/cb_img_2500_it_0/raw/main/foil_cb_img_2500_it.json",
    "id_item": "foil_cb_img_2500_it",
    "id_album": "1958080175",
    "english": "foil",
    "list_mean": [
      "làm thất bại (một âm mưu, một kế hoạch…)",
      "lá (kim loại)",
      "người hay vật tôn người hay vật khác lên (khi so sánh)",
      "kiếm bịt đầu"
    ],
    "cau_en": "",
    "cau_vn": "",
    "hash_code_list_mean": "1697257274",
    "list_img": [
      {
        "link_thumb": "https://live.staticflickr.com/65535/51810054610_39be0ddf13_n.jpg",
        "link_img": "https://live.staticflickr.com/65535/51810054610_422e46a92a_o.png",
        "id_image": "foil_239248"
      },
      {
        "link_thumb": "https://live.staticflickr.com/65535/51809317986_7e593be906_n.jpg",
        "link_img": "https://live.staticflickr.com/65535/51809317986_83dc04acc7_o.png",
        "id_image": "foil_4802431"
      }
    ],
    "hash_code_list_img": "-1363236129"
  },
  {
    "link_it": "https://github.com/lmbstudiocontact/cb_img_2500_it_2/raw/main/review_cb_img_2500_it.json",
    "id_item": "review_cb_img_2500_it",
    "id_album": "1958080175",
    "english": "review",
    "list_mean": [
      "bài phê bình",
      "cuộc duyệt binh",
      "sự xem xét lại",
      "xem xét; duyệt binh",
      "xem xét lại",
      "xem lại"
    ],
    "cau_en": "",
    "cau_vn": "",
    "hash_code_list_mean": "853032006",
    "list_img": [
      {
        "link_thumb": "https://live.staticflickr.com/65535/51810085720_299fe0a873_n.jpg",
        "link_img": "https://live.staticflickr.com/65535/51810085720_faabd8e016_o.png",
        "id_image": "review_3168643"
      },
      {
        "link_thumb": "https://live.staticflickr.com/65535/51809348426_5c18605632_n.jpg",
        "link_img": "https://live.staticflickr.com/65535/51809348426_96f3e258a9_o.png",
        "id_image": "review_3827297"
      },
      {
        "link_thumb": "https://live.staticflickr.com/65535/51808393357_675ce448dd_n.jpg",
        "link_img": "https://live.staticflickr.com/65535/51808393357_7417bcd198_o.png",
        "id_image": "review_448720"
      }
    ],
    "hash_code_list_img": "1990694658"
  },
  {
    "link_it": "https://github.com/lmbstudiocontact/cb_img_2500_it_2/raw/main/shift_cb_img_2500_it.json",
    "id_item": "shift_cb_img_2500_it",
    "id_album": "1958080175",
    "english": "shift",
    "list_mean": [
      "đổi chỗ, di chuyển",
      "chuyển , giao",
      "trút bỏ, trút lên",
      "sự thay đổi",
      "sự luân phiên",
      "ca, kíp"
    ],
    "cau_en": "",
    "cau_vn": "",
    "hash_code_list_mean": "236087871",
    "list_img": [
      {
        "link_thumb": "https://live.staticflickr.com/65535/51809459678_8a095b6954_n.jpg",
        "link_img": "https://live.staticflickr.com/65535/51809459678_bee60630f0_o.png",
        "id_image": "shift_1898739"
      },
      {
        "link_thumb": "https://live.staticflickr.com/65535/51808389762_9883251656_n.jpg",
        "link_img": "https://live.staticflickr.com/65535/51808389762_db46515341_o.png",
        "id_image": "shift_3203154"
      },
      {
        "link_thumb": "https://live.staticflickr.com/65535/51808389877_d8f5010f5b_n.jpg",
        "link_img": "https://live.staticflickr.com/65535/51808389877_a1647e5a06_o.png",
        "id_image": "shift_429967"
      },
      {
        "link_thumb": "https://live.staticflickr.com/65535/51810082380_65039cc8d1_n.jpg",
        "link_img": "https://live.staticflickr.com/65535/51810082380_f0e300b336_o.png",
        "id_image": "shift_670864"
      }
    ],
    "hash_code_list_img": "-1241348056"
  },
  {
    "link_it": "https://github.com/lmbstudiocontact/cb_img_2500_it_1/raw/main/perm_cb_img_2500_it.json",
    "id_item": "perm_cb_img_2500_it",
    "id_album": "1958080175",
    "english": "perm",
    "list_mean": [
      "quăn",
      "làm tóc quăn"
    ],
    "cau_en": "",
    "cau_vn": "",
    "hash_code_list_mean": "214770244",
    "list_img": [
      {
        "link_thumb": "https://live.staticflickr.com/65535/51809320426_c9a49b8871_n.jpg",
        "link_img": "https://live.staticflickr.com/65535/51809320426_c40cfccf46_o.png",
        "id_image": "perm_3125044"
      }
    ],
    "hash_code_list_img": "1851741335"
  },
  {
    "link_it": "https://github.com/lmbstudiocontact/cb_img_2500_it_1/raw/main/handsome_cb_img_2500_it.json",
    "id_item": "handsome_cb_img_2500_it",
    "id_album": "1958080175",
    "english": "handsome",
    "list_mean": [
      "đẹp trai",
      "hào phóng; rộng rãi"
    ],
    "cau_en": "",
    "cau_vn": "",
    "hash_code_list_mean": "113222475",
    "list_img": [
      {
        "link_thumb": "https://live.staticflickr.com/65535/51808390497_6023090e61_n.jpg",
        "link_img": "https://live.staticflickr.com/65535/51808390497_dc333b111b_o.png",
        "id_image": "handsome_2897006"
      },
      {
        "link_thumb": "https://live.staticflickr.com/65535/51809700604_ce334daa57_n.jpg",
        "link_img": "https://live.staticflickr.com/65535/51809700604_37093dfcd1_o.png",
        "id_image": "handsome_3891309"
      }
    ],
    "hash_code_list_img": "-716131777"
  },
  {
    "link_it": "https://github.com/lmbstudiocontact/cb_img_2500_it_1/raw/main/palm_cb_img_2500_it.json",
    "id_item": "palm_cb_img_2500_it",
    "id_album": "1958080175",
    "english": "palm",
    "list_mean": [
      "lòng bàn tay",
      "cây cọ"
    ],
    "cau_en": "",
    "cau_vn": "",
    "hash_code_list_mean": "847360566",
    "list_img": [
      {
        "link_thumb": "https://live.staticflickr.com/65535/51810072795_500b969cd8_n.jpg",
        "link_img": "https://live.staticflickr.com/65535/51810072795_99533af9a0_o.png",
        "id_image": "palm_209232"
      },
      {
        "link_thumb": "https://live.staticflickr.com/65535/51809691034_b0c19c0409_n.jpg",
        "link_img": "https://live.staticflickr.com/65535/51809691034_d78a4a7505_o.png",
        "id_image": "palm_2287892"
      },
      {
        "link_thumb": "https://live.staticflickr.com/65535/51808380837_205af20d0e_n.jpg",
        "link_img": "https://live.staticflickr.com/65535/51808380837_a54479da43_o.png",
        "id_image": "palm_3332698"
      },
      {
        "link_thumb": "https://live.staticflickr.com/65535/51810072750_d3372bb4f5_n.jpg",
        "link_img": "https://live.staticflickr.com/65535/51810072750_5ca930de2e_o.png",
        "id_image": "palm_882888"
      }
    ],
    "hash_code_list_img": "-1684606873"
  },
  {
    "link_it": "https://github.com/lmbstudiocontact/cb_img_2500_it_1/raw/main/humanitarian_cb_img_2500_it.json",
    "id_item": "humanitarian_cb_img_2500_it",
    "id_album": "1958080175",
    "english": "humanitarian",
    "list_mean": [
      "nhân đạo",
      "sự nhân đạo"
    ],
    "cau_en": "",
    "cau_vn": "",
    "hash_code_list_mean": "38643043",
    "list_img": [
      {
        "link_thumb": "https://live.staticflickr.com/65535/51810064860_0586e5193f_n.jpg",
        "link_img": "https://live.staticflickr.com/65535/51810064860_5ab41f2e5a_o.png",
        "id_image": "humanitarian_1378696"
      },
      {
        "link_thumb": "https://live.staticflickr.com/65535/51809328071_5cc0669e62_n.jpg",
        "link_img": "https://live.staticflickr.com/65535/51809328071_8c16c35e50_o.png",
        "id_image": "humanitarian_2871600"
      },
      {
        "link_thumb": "https://live.staticflickr.com/65535/51808372792_84aaa14bfd_n.jpg",
        "link_img": "https://live.staticflickr.com/65535/51808372792_f10d25a18b_o.png",
        "id_image": "humanitarian_5102260"
      }
    ],
    "hash_code_list_img": "-1744088251"
  },
  {
    "link_it": "https://github.com/lmbstudiocontact/cb_img_2500_it_0/raw/main/exhibit_cb_img_2500_it.json",
    "id_item": "exhibit_cb_img_2500_it",
    "id_album": "1958080175",
    "english": "exhibit",
    "list_mean": [
      "triển lãm",
      "biểu lộ",
      "vật triển lãm",
      "tang vật"
    ],
    "cau_en": "",
    "cau_vn": "",
    "hash_code_list_mean": "1485440195",
    "list_img": [
      {
        "link_thumb": "https://live.staticflickr.com/65535/51809426078_61dc59728a_n.jpg",
        "link_img": "https://live.staticflickr.com/65535/51809426078_6223dc1e33_o.png",
        "id_image": "exhibit_223257"
      }
    ],
    "hash_code_list_img": "591589918"
  },
  {
    "link_it": "https://github.com/lmbstudiocontact/cb_img_2500_it_0/raw/main/decision_cb_img_2500_it.json",
    "id_item": "decision_cb_img_2500_it",
    "id_album": "1958080175",
    "english": "decision",
    "list_mean": [
      "quyết định"
    ],
    "cau_en": "",
    "cau_vn": "",
    "hash_code_list_mean": "-327382423",
    "list_img": [
      {
        "link_thumb": "https://live.staticflickr.com/65535/51810044420_97b4fa5474_n.jpg",
        "link_img": "https://live.staticflickr.com/65535/51810044420_a83816e497_o.png",
        "id_image": "decision_1900209"
      },
      {
        "link_thumb": "https://live.staticflickr.com/65535/51809662719_d1549bc1aa_n.jpg",
        "link_img": "https://live.staticflickr.com/65535/51809662719_2be638c65c_o.png",
        "id_image": "decision_1900265"
      },
      {
        "link_thumb": "https://live.staticflickr.com/65535/51808351577_a439380e75_n.jpg",
        "link_img": "https://live.staticflickr.com/65535/51808351577_de3215af68_o.png",
        "id_image": "decision_993690"
      }
    ],
    "hash_code_list_img": "666648769"
  },
  {
    "link_it": "https://github.com/lmbstudiocontact/cb_img_2500_it_1/raw/main/humanity_cb_img_2500_it.json",
    "id_item": "humanity_cb_img_2500_it",
    "id_album": "1958080175",
    "english": "humanity",
    "list_mean": [
      "lòng nhân đạo",
      "loài người"
    ],
    "cau_en": "",
    "cau_vn": "",
    "hash_code_list_mean": "142423754",
    "list_img": [
      {
        "link_thumb": "https://live.staticflickr.com/65535/51808372792_84aaa14bfd_n.jpg",
        "link_img": "https://live.staticflickr.com/65535/51808372792_f10d25a18b_o.png",
        "id_image": "humanitarian_5102260"
      },
      {
        "link_thumb": "https://live.staticflickr.com/65535/51808372932_8d314a702b_n.jpg",
        "link_img": "https://live.staticflickr.com/65535/51808372932_f959cfdd32_o.png",
        "id_image": "human_2640779"
      }
    ],
    "hash_code_list_img": "226152296"
  },
  {
    "link_it": "https://github.com/lmbstudiocontact/cb_img_2500_it_2/raw/main/what_cb_img_2500_it.json",
    "id_item": "what_cb_img_2500_it",
    "id_album": "1958080175",
    "english": "what",
    "list_mean": [
      "gì",
      "sử dụng trong câu cảm thán bày tỏ sự ngạc nhiên",
      "những thứ",
      "những điều"
    ],
    "cau_en": "",
    "cau_vn": "",
    "hash_code_list_mean": "-2144774125",
    "list_img": [
      {
        "link_thumb": "https://live.staticflickr.com/65535/51809331721_f94cb2df59_n.jpg",
        "link_img": "https://live.staticflickr.com/65535/51809331721_805aed9fcc_o.png",
        "id_image": "what_4471136"
      },
      {
        "link_thumb": "https://live.staticflickr.com/65535/51809686664_8883159555_n.jpg",
        "link_img": "https://live.staticflickr.com/65535/51809686664_9a95879879_o.png",
        "id_image": "what_5359837"
      }
    ],
    "hash_code_list_img": "-2122425820"
  },
  {
    "link_it": "https://github.com/lmbstudiocontact/cb_img_2500_it_1/raw/main/knife_cb_img_2500_it.json",
    "id_item": "knife_cb_img_2500_it",
    "id_album": "1958080175",
    "english": "knife",
    "list_mean": [
      "con dao",
      "dao găm",
      "đâm bằng dao"
    ],
    "cau_en": "",
    "cau_vn": "",
    "hash_code_list_mean": "-53388850",
    "list_img": [
      {
        "link_thumb": "https://live.staticflickr.com/65535/51809440693_f8428469ab_n.jpg",
        "link_img": "https://live.staticflickr.com/65535/51809440693_fb3ae84225_o.png",
        "id_image": "knife_297832"
      },
      {
        "link_thumb": "https://live.staticflickr.com/65535/51809440673_7d0396a57d_n.jpg",
        "link_img": "https://live.staticflickr.com/65535/51809440673_522d8d1981_o.png",
        "id_image": "knife_333549"
      },
      {
        "link_thumb": "https://live.staticflickr.com/65535/51808370422_571ec1dcc2_n.jpg",
        "link_img": "https://live.staticflickr.com/65535/51808370422_f4569a4727_o.png",
        "id_image": "knife_535039"
      }
    ],
    "hash_code_list_img": "75582107"
  },
  {
    "link_it": "https://github.com/lmbstudiocontact/cb_img_2500_it_0/raw/main/contact_cb_img_2500_it.json",
    "id_item": "contact_cb_img_2500_it",
    "id_album": "1958080175",
    "english": "contact",
    "list_mean": [
      "sự tiếp xúc",
      "sự liên lạc",
      "đầu mối liên lạc",
      "chỗ tiếp xúc",
      "người có thể truyền bệnh",
      "người, thiết bị liên lạc",
      "liên lạc"
    ],
    "cau_en": "",
    "cau_vn": "",
    "hash_code_list_mean": "355996239",
    "list_img": [
      {
        "link_thumb": "https://live.staticflickr.com/65535/51809308301_38e181b122_n.jpg",
        "link_img": "https://live.staticflickr.com/65535/51809308301_c9c1a8ae03_o.png",
        "id_image": "contact_1418570"
      },
      {
        "link_thumb": "https://live.staticflickr.com/65535/51809308286_7300f06919_n.jpg",
        "link_img": "https://live.staticflickr.com/65535/51809308286_1de35616fc_o.png",
        "id_image": "contact_1455096"
      },
      {
        "link_thumb": "https://live.staticflickr.com/65535/51809308211_ee1e9dc50c_n.jpg",
        "link_img": "https://live.staticflickr.com/65535/51809308211_8e83283be1_o.png",
        "id_image": "contact_1871100"
      },
      {
        "link_thumb": "https://live.staticflickr.com/65535/51810045150_5c656c504a_n.jpg",
        "link_img": "https://live.staticflickr.com/65535/51810045150_5f1a9ed084_o.png",
        "id_image": "contact_3130709"
      }
    ],
    "hash_code_list_img": "1846661565"
  },
  {
    "link_it": "https://github.com/lmbstudiocontact/cb_img_2500_it_2/raw/main/social_cb_img_2500_it.json",
    "id_item": "social_cb_img_2500_it",
    "id_album": "1958080175",
    "english": "social",
    "list_mean": [
      "có tính chất xã hội",
      "thuộc quan hệ gữa người và người, thuộc xã hội",
      "sống thành đàn, quần thể",
      "tình bạn bè và sự giải trí"
    ],
    "cau_en": "",
    "cau_vn": "",
    "hash_code_list_mean": "1438948807",
    "list_img": [
      {
        "link_thumb": "https://live.staticflickr.com/65535/51809442728_6ffcd458ac_n.jpg",
        "link_img": "https://live.staticflickr.com/65535/51809442728_f7c0c55242_o.png",
        "id_image": "social_780563"
      },
      {
        "link_thumb": "https://live.staticflickr.com/65535/51809327661_344d88ed45_n.jpg",
        "link_img": "https://live.staticflickr.com/65535/51809327661_ae41058540_o.png",
        "id_image": "social_992641"
      }
    ],
    "hash_code_list_img": "-1076140654"
  },
  {
    "link_it": "https://github.com/lmbstudiocontact/cb_img_2500_it_2/raw/main/retail_cb_img_2500_it.json",
    "id_item": "retail_cb_img_2500_it",
    "id_album": "1958080175",
    "english": "retail",
    "list_mean": [
      "bán lẻ",
      "thuộc bán lẻ",
      "ngành bán lẻ"
    ],
    "cau_en": "",
    "cau_vn": "",
    "hash_code_list_mean": "925211369",
    "list_img": [
      {
        "link_thumb": "https://live.staticflickr.com/65535/51809349616_e6a08cf707_n.jpg",
        "link_img": "https://live.staticflickr.com/65535/51809349616_69df9c29b0_o.png",
        "id_image": "retail_1353752"
      },
      {
        "link_thumb": "https://live.staticflickr.com/65535/51809704269_090367bc2b_n.jpg",
        "link_img": "https://live.staticflickr.com/65535/51809704269_f7e3d3e370_o.png",
        "id_image": "retail_2037284"
      },
      {
        "link_thumb": "https://live.staticflickr.com/65535/51809464268_cfeb84805b_n.jpg",
        "link_img": "https://live.staticflickr.com/65535/51809464268_2075c8af6c_o.png",
        "id_image": "retail_6206766"
      }
    ],
    "hash_code_list_img": "-1977935143"
  },
  {
    "link_it": "https://github.com/lmbstudiocontact/cb_img_2500_it_0/raw/main/duel_cb_img_2500_it.json",
    "id_item": "duel_cb_img_2500_it",
    "id_album": "1958080175",
    "english": "duel",
    "list_mean": [
      "cuộc đấu súng hoặc đấu kiếm",
      "cuộc đấu giữa hai người hoặc hai bên",
      "đọ súng hoặc đọ kiếm tay đôi"
    ],
    "cau_en": "",
    "cau_vn": "",
    "hash_code_list_mean": "1312231244",
    "list_img": [
      {
        "link_thumb": "https://live.staticflickr.com/65535/51809450603_291d95f90c_n.jpg",
        "link_img": "https://live.staticflickr.com/65535/51809450603_4225f11a07_o.png",
        "id_image": "duel_3570424"
      },
      {
        "link_thumb": "https://live.staticflickr.com/65535/51809450583_c0ac0b95a9_n.jpg",
        "link_img": "https://live.staticflickr.com/65535/51809450583_c579177f89_o.png",
        "id_image": "duel_3746461"
      }
    ],
    "hash_code_list_img": "363340298"
  },
  {
    "link_it": "https://github.com/lmbstudiocontact/cb_img_2500_it_1/raw/main/merchant_cb_img_2500_it.json",
    "id_item": "merchant_cb_img_2500_it",
    "id_album": "1958080175",
    "english": "merchant",
    "list_mean": [
      "thương gia"
    ],
    "cau_en": "",
    "cau_vn": "",
    "hash_code_list_mean": "629619868",
    "list_img": [
      {
        "link_thumb": "https://live.staticflickr.com/65535/51809701409_a38dbfcaa4_n.jpg",
        "link_img": "https://live.staticflickr.com/65535/51809701409_926723f4c8_o.png",
        "id_image": "merchant_1100474"
      },
      {
        "link_thumb": "https://live.staticflickr.com/65535/51810083945_933164a965_n.jpg",
        "link_img": "https://live.staticflickr.com/65535/51810083945_4670e27207_o.png",
        "id_image": "merchant_2104181"
      },
      {
        "link_thumb": "https://live.staticflickr.com/65535/51810083920_801c44cc14_n.jpg",
        "link_img": "https://live.staticflickr.com/65535/51810083920_2bff45452a_o.png",
        "id_image": "merchant_4016132"
      },
      {
        "link_thumb": "https://live.staticflickr.com/65535/51809461233_03a1a02258_n.jpg",
        "link_img": "https://live.staticflickr.com/65535/51809461233_fa5ac72e96_o.png",
        "id_image": "merchant_4633140"
      }
    ],
    "hash_code_list_img": "-1742556623"
  },
  {
    "link_it": "https://github.com/lmbstudiocontact/cb_img_2500_it_0/raw/main/density_cb_img_2500_it.json",
    "id_item": "density_cb_img_2500_it",
    "id_album": "1958080175",
    "english": "density",
    "list_mean": [
      "mật độ",
      "tỷ trọng"
    ],
    "cau_en": "",
    "cau_vn": "",
    "hash_code_list_mean": "970689528",
    "list_img": [
      {
        "link_thumb": "https://live.staticflickr.com/65535/51809332356_0098b2890e_n.jpg",
        "link_img": "https://live.staticflickr.com/65535/51809332356_2d2656916d_o.png",
        "id_image": "density_4176615"
      },
      {
        "link_thumb": "https://live.staticflickr.com/65535/51810069045_2978524407_n.jpg",
        "link_img": "https://live.staticflickr.com/65535/51810069045_1cd04eb58e_o.png",
        "id_image": "density_5825237"
      },
      {
        "link_thumb": "https://live.staticflickr.com/65535/51808377012_748d9cc4c5_n.jpg",
        "link_img": "https://live.staticflickr.com/65535/51808377012_66741992cb_o.png",
        "id_image": "density_5931534"
      },
      {
        "link_thumb": "https://live.staticflickr.com/65535/51810068985_c575f02248_n.jpg",
        "link_img": "https://live.staticflickr.com/65535/51810068985_c74e58d016_o.png",
        "id_image": "density_6080884"
      }
    ],
    "hash_code_list_img": "947194588"
  },
  {
    "link_it": "https://github.com/lmbstudiocontact/cb_img_2500_it_0/raw/main/crease_cb_img_2500_it.json",
    "id_item": "crease_cb_img_2500_it",
    "id_album": "1958080175",
    "english": "crease",
    "list_mean": [
      "nếp gấp",
      "vạch trắng ở hai đầu sân",
      "làm nhàu"
    ],
    "cau_en": "",
    "cau_vn": "",
    "hash_code_list_mean": "-255615425",
    "list_img": [
      {
        "link_thumb": "https://live.staticflickr.com/65535/51809322441_ed6419f016_n.jpg",
        "link_img": "https://live.staticflickr.com/65535/51809322441_f06910dddd_o.png",
        "id_image": "crease_2856482"
      }
    ],
    "hash_code_list_img": "1662549378"
  },
  {
    "link_it": "https://github.com/lmbstudiocontact/cb_img_2500_it_1/raw/main/page_cb_img_2500_it.json",
    "id_item": "page_cb_img_2500_it",
    "id_album": "1958080175",
    "english": "page",
    "list_mean": [
      "trang sách",
      "cậu bé phục vụ tại khách sạn",
      "tiểu đồng",
      "gọi loa nhắn tin"
    ],
    "cau_en": "",
    "cau_vn": "",
    "hash_code_list_mean": "-1500492319",
    "list_img": [
      {
        "link_thumb": "https://live.staticflickr.com/65535/51809452158_1c11bdfb19_n.jpg",
        "link_img": "https://live.staticflickr.com/65535/51809452158_ac5d20d19d_o.png",
        "id_image": "page_485245"
      },
      {
        "link_thumb": "https://live.staticflickr.com/65535/51808382297_375621451d_n.jpg",
        "link_img": "https://live.staticflickr.com/65535/51808382297_d53bf58130_o.png",
        "id_image": "page_4905252"
      },
      {
        "link_thumb": "https://live.staticflickr.com/65535/51809452123_79412d1b67_n.jpg",
        "link_img": "https://live.staticflickr.com/65535/51809452123_de12c829ea_o.png",
        "id_image": "page_893427"
      }
    ],
    "hash_code_list_img": "1726706876"
  },
  {
    "link_it": "https://github.com/lmbstudiocontact/cb_img_2500_it_1/raw/main/jelly_cb_img_2500_it.json",
    "id_item": "jelly_cb_img_2500_it",
    "id_album": "1958080175",
    "english": "jelly",
    "list_mean": [
      "thạch",
      "mứt",
      "giống như thạch",
      "mứt cô đặc"
    ],
    "cau_en": "",
    "cau_vn": "",
    "hash_code_list_mean": "1958287565",
    "list_img": [
      {
        "link_thumb": "https://live.staticflickr.com/65535/51809335096_9e605a4f47_n.jpg",
        "link_img": "https://live.staticflickr.com/65535/51809335096_990cf958d4_o.png",
        "id_image": "jelly_1398525"
      },
      {
        "link_thumb": "https://live.staticflickr.com/65535/51809690204_4395617076_n.jpg",
        "link_img": "https://live.staticflickr.com/65535/51809690204_399ac94cee_o.png",
        "id_image": "jelly_2002748"
      },
      {
        "link_thumb": "https://live.staticflickr.com/65535/51808380082_68158b1afa_n.jpg",
        "link_img": "https://live.staticflickr.com/65535/51808380082_ba92a55b5f_o.png",
        "id_image": "jelly_6299706"
      }
    ],
    "hash_code_list_img": "934311047"
  },
  {
    "link_it": "https://github.com/lmbstudiocontact/cb_img_2500_it_2/raw/main/wood_cb_img_2500_it.json",
    "id_item": "wood_cb_img_2500_it",
    "id_album": "1958080175",
    "english": "wood",
    "list_mean": [
      "gỗ",
      "rừng",
      "gậy đánh gôn"
    ],
    "cau_en": "",
    "cau_vn": "",
    "hash_code_list_mean": "-1624233899",
    "list_img": [
      {
        "link_thumb": "https://live.staticflickr.com/65535/51810071930_02e9b48e5f_n.jpg",
        "link_img": "https://live.staticflickr.com/65535/51810071930_0b6c8bc605_o.png",
        "id_image": "wood_2153138"
      },
      {
        "link_thumb": "https://live.staticflickr.com/65535/51809450053_2d2b012539_n.jpg",
        "link_img": "https://live.staticflickr.com/65535/51809450053_1046686522_o.png",
        "id_image": "wood_878460"
      }
    ],
    "hash_code_list_img": "-807032770"
  },
  {
    "link_it": "https://github.com/lmbstudiocontact/cb_img_2500_it_0/raw/main/fawn_cb_img_2500_it.json",
    "id_item": "fawn_cb_img_2500_it",
    "id_album": "1958080175",
    "english": "fawn",
    "list_mean": [
      "hươu, nai nhỏ",
      "có màu nâu vàng nhạt",
      "xun xoe; bợ đỡ",
      "vẫy đuôi mừng (chó)"
    ],
    "cau_en": "",
    "cau_vn": "",
    "hash_code_list_mean": "71504701",
    "list_img": [
      {
        "link_thumb": "https://live.staticflickr.com/65535/51809333896_61ebbc79d3_n.jpg",
        "link_img": "https://live.staticflickr.com/65535/51809333896_aa1974c5d2_o.png",
        "id_image": "fawn_5150889"
      }
    ],
    "hash_code_list_img": "265262404"
  },
  {
    "link_it": "https://github.com/lmbstudiocontact/cb_img_2500_it_1/raw/main/patient_cb_img_2500_it.json",
    "id_item": "patient_cb_img_2500_it",
    "id_album": "1958080175",
    "english": "patient",
    "list_mean": [
      "kiên nhẫn",
      "bệnh nhân"
    ],
    "cau_en": "",
    "cau_vn": "",
    "hash_code_list_mean": "715815277",
    "list_img": [
      {
        "link_thumb": "https://live.staticflickr.com/65535/51810064430_b63859716a_n.jpg",
        "link_img": "https://live.staticflickr.com/65535/51810064430_1b294136de_o.png",
        "id_image": "patient_2454801"
      },
      {
        "link_thumb": "https://live.staticflickr.com/65535/51809442718_091eef64b5_n.jpg",
        "link_img": "https://live.staticflickr.com/65535/51809442718_fbfdfde391_o.png",
        "id_image": "patient_5278459"
      },
      {
        "link_thumb": "https://live.staticflickr.com/65535/51808372492_fe220b2452_n.jpg",
        "link_img": "https://live.staticflickr.com/65535/51808372492_36ced291b8_o.png",
        "id_image": "patient_706192"
      }
    ],
    "hash_code_list_img": "1865097014"
  },
  {
    "link_it": "https://github.com/lmbstudiocontact/cb_img_2500_it_2/raw/main/wake_cb_img_2500_it.json",
    "id_item": "wake_cb_img_2500_it",
    "id_album": "1958080175",
    "english": "wake",
    "list_mean": [
      "tỉnh giấc",
      "đường rẽ nước"
    ],
    "cau_en": "",
    "cau_vn": "",
    "hash_code_list_mean": "-926809114",
    "list_img": [
      {
        "link_thumb": "https://live.staticflickr.com/65535/51809693969_e4cd062c79_n.jpg",
        "link_img": "https://live.staticflickr.com/65535/51809693969_ff5fdf35f8_o.png",
        "id_image": "wake_5284836"
      }
    ],
    "hash_code_list_img": "2114553576"
  },
  {
    "link_it": "https://github.com/lmbstudiocontact/cb_img_2500_it_1/raw/main/obituary_cb_img_2500_it.json",
    "id_item": "obituary_cb_img_2500_it",
    "id_album": "1958080175",
    "english": "obituary",
    "list_mean": [
      "cáo phó"
    ],
    "cau_en": "",
    "cau_vn": "",
    "hash_code_list_mean": "-81281845",
    "list_img": [
      {
        "link_thumb": "https://live.staticflickr.com/65535/51809434213_f14e5c5d8b_n.jpg",
        "link_img": "https://live.staticflickr.com/65535/51809434213_eb2ca4c6ca_o.png",
        "id_image": "obituary_1450718"
      },
      {
        "link_thumb": "https://live.staticflickr.com/65535/51809318976_f853d35696_n.jpg",
        "link_img": "https://live.staticflickr.com/65535/51809318976_0c4c9c7d9e_o.png",
        "id_image": "obituary_6001064"
      }
    ],
    "hash_code_list_img": "-1538389451"
  },
  {
    "link_it": "https://github.com/lmbstudiocontact/cb_img_2500_it_0/raw/main/climate_cb_img_2500_it.json",
    "id_item": "climate_cb_img_2500_it",
    "id_album": "1958080175",
    "english": "climate",
    "list_mean": [
      "khí hậu",
      "không khí"
    ],
    "cau_en": "",
    "cau_vn": "",
    "hash_code_list_mean": "-663904991",
    "list_img": [
      {
        "link_thumb": "https://live.staticflickr.com/65535/51808377112_dc0be3abb8_n.jpg",
        "link_img": "https://live.staticflickr.com/65535/51808377112_865dbff371_o.png",
        "id_image": "climate_1730197"
      },
      {
        "link_thumb": "https://live.staticflickr.com/65535/51808377072_2f670fb2ed_n.jpg",
        "link_img": "https://live.staticflickr.com/65535/51808377072_8731a89561_o.png",
        "id_image": "climate_4215414"
      },
      {
        "link_thumb": "https://live.staticflickr.com/65535/51808376997_73324cfebd_n.jpg",
        "link_img": "https://live.staticflickr.com/65535/51808376997_d32ed9fb7a_o.png",
        "id_image": "climate_5264789"
      },
      {
        "link_thumb": "https://live.staticflickr.com/65535/51808376982_b733530e3e_n.jpg",
        "link_img": "https://live.staticflickr.com/65535/51808376982_3345f07b07_o.png",
        "id_image": "climate_5493014"
      }
    ],
    "hash_code_list_img": "-2113301299"
  },
  {
    "link_it": "https://github.com/lmbstudiocontact/cb_img_2500_it_0/raw/main/contagious_cb_img_2500_it.json",
    "id_item": "contagious_cb_img_2500_it",
    "id_album": "1958080175",
    "english": "contagious",
    "list_mean": [
      "dễ lây"
    ],
    "cau_en": "",
    "cau_vn": "",
    "hash_code_list_mean": "1548619683",
    "list_img": [
      {
        "link_thumb": "https://live.staticflickr.com/65535/51809663244_eb18b63f24_n.jpg",
        "link_img": "https://live.staticflickr.com/65535/51809663244_739bf067f6_o.png",
        "id_image": "contagious_2688364"
      },
      {
        "link_thumb": "https://live.staticflickr.com/65535/51809307971_6177fb3c6e_n.jpg",
        "link_img": "https://live.staticflickr.com/65535/51809307971_e3d5262846_o.png",
        "id_image": "contagious_2688379"
      },
      {
        "link_thumb": "https://live.staticflickr.com/65535/51809663174_d0ae91e816_n.jpg",
        "link_img": "https://live.staticflickr.com/65535/51809663174_a86c8b1ec4_o.png",
        "id_image": "contagious_2720270"
      },
      {
        "link_thumb": "https://live.staticflickr.com/65535/51809423068_fe6c5d5dd4_n.jpg",
        "link_img": "https://live.staticflickr.com/65535/51809423068_8859dffa49_o.png",
        "id_image": "contagious_2927196"
      },
      {
        "link_thumb": "https://live.staticflickr.com/65535/51809307856_e0e57e4afa_n.jpg",
        "link_img": "https://live.staticflickr.com/65535/51809307856_724e95394e_o.png",
        "id_image": "contagious_3182061"
      }
    ],
    "hash_code_list_img": "1018899106"
  },
  {
    "link_it": "https://github.com/lmbstudiocontact/cb_img_2500_it_0/raw/main/drag_cb_img_2500_it.json",
    "id_item": "drag_cb_img_2500_it",
    "id_album": "1958080175",
    "english": "drag",
    "list_mean": [
      "lôi kéo",
      "kéo lê",
      "lê",
      "mò bằng lưới",
      "kéo dài quá",
      "sự ngáng trở",
      "sự rít một hơi thuốc lá",
      "người hoặc vật gây buồn chán",
      "quần áo phụ nữ do người đàn ông mặc"
    ],
    "cau_en": "",
    "cau_vn": "",
    "hash_code_list_mean": "2147127028",
    "list_img": [
      {
        "link_thumb": "https://live.staticflickr.com/65535/51809307051_5178710213_n.jpg",
        "link_img": "https://live.staticflickr.com/65535/51809307051_c3e34d3219_o.png",
        "id_image": "drag_1196456"
      },
      {
        "link_thumb": "https://live.staticflickr.com/65535/51808351192_bb7b80f606_n.jpg",
        "link_img": "https://live.staticflickr.com/65535/51808351192_fd6a4cf576_o.png",
        "id_image": "drag_247733"
      },
      {
        "link_thumb": "https://live.staticflickr.com/65535/51809422188_7787547394_n.jpg",
        "link_img": "https://live.staticflickr.com/65535/51809422188_9d80c85424_o.png",
        "id_image": "drag_4430332"
      }
    ],
    "hash_code_list_img": "1755877320"
  },
  {
    "link_it": "https://github.com/lmbstudiocontact/cb_img_2500_it_1/raw/main/peace_cb_img_2500_it.json",
    "id_item": "peace_cb_img_2500_it",
    "id_album": "1958080175",
    "english": "peace",
    "list_mean": [
      "hoà bình",
      "sự yên bình"
    ],
    "cau_en": "",
    "cau_vn": "",
    "hash_code_list_mean": "-41406881",
    "list_img": [
      {
        "link_thumb": "https://live.staticflickr.com/65535/51808370372_5a8d98aa27_n.jpg",
        "link_img": "https://live.staticflickr.com/65535/51808370372_5118a839c4_o.png",
        "id_image": "peace_209211"
      },
      {
        "link_thumb": "https://live.staticflickr.com/65535/51809440538_8aa7fff331_n.jpg",
        "link_img": "https://live.staticflickr.com/65535/51809440538_d0bdaa6502_o.png",
        "id_image": "peace_209228"
      },
      {
        "link_thumb": "https://live.staticflickr.com/65535/51810062275_1bcd97aaaf_n.jpg",
        "link_img": "https://live.staticflickr.com/65535/51810062275_c409bc63c6_o.png",
        "id_image": "peace_750482"
      }
    ],
    "hash_code_list_img": "87629576"
  },
  {
    "link_it": "https://github.com/lmbstudiocontact/cb_img_2500_it_0/raw/main/cherry_cb_img_2500_it.json",
    "id_item": "cherry_cb_img_2500_it",
    "id_album": "1958080175",
    "english": "cherry",
    "list_mean": [
      "quả anh đào"
    ],
    "cau_en": "",
    "cau_vn": "",
    "hash_code_list_mean": "-1812218215",
    "list_img": [
      {
        "link_thumb": "https://live.staticflickr.com/65535/51809425708_279e98478f_n.jpg",
        "link_img": "https://live.staticflickr.com/65535/51809425708_9bd4e641b3_o.png",
        "id_image": "cherry_4796217"
      }
    ],
    "hash_code_list_img": "383882734"
  }
]