[
  {
    "link_it": "https://github.com/lmbstudiocontact/cb_img_2500_it_1/raw/main/mark_cb_img_2500_it.json",
    "id_item": "mark_cb_img_2500_it",
    "id_album": "570943428",
    "english": "mark",
    "list_mean": [
      "đồng Mác (Đức)",
      "điểm số",
      "vết bẩn",
      "dấu vết",
      "dấu chữ thập (của những người không biết viết",
      "biểu hiện",
      "đánh dấu",
      "chấm điểm",
      "chứng tỏ",
      "ghi chép",
      "chú ý"
    ],
    "cau_en": "",
    "cau_vn": "",
    "hash_code_list_mean": "-1252081994",
    "list_img": [
      {
        "link_thumb": "https://live.staticflickr.com/65535/51810059920_a084acf5c3_n.jpg",
        "link_img": "https://live.staticflickr.com/65535/51810059920_11d0336ec2_o.png",
        "id_image": "mark_1119875"
      },
      {
        "link_thumb": "https://live.staticflickr.com/65535/51809678364_d417e5c85a_n.jpg",
        "link_img": "https://live.staticflickr.com/65535/51809678364_229e29ace4_o.png",
        "id_image": "mark_4469819"
      }
    ],
    "hash_code_list_img": "2116855367"
  },
  {
    "link_it": "https://github.com/lmbstudiocontact/cb_img_2500_it_0/raw/main/evolution_cb_img_2500_it.json",
    "id_item": "evolution_cb_img_2500_it",
    "id_album": "570943428",
    "english": "evolution",
    "list_mean": [
      "sự tiến triển",
      "sự tiến hoá"
    ],
    "cau_en": "",
    "cau_vn": "",
    "hash_code_list_mean": "-323170171",
    "list_img": [
      {
        "link_thumb": "https://live.staticflickr.com/65535/51808357197_0c24033872_n.jpg",
        "link_img": "https://live.staticflickr.com/65535/51808357197_f85783305a_o.png",
        "id_image": "evolution_2586952"
      },
      {
        "link_thumb": "https://live.staticflickr.com/65535/51810049675_e5c9033f13_n.jpg",
        "link_img": "https://live.staticflickr.com/65535/51810049675_44e16a0f84_o.png",
        "id_image": "evolution_2597668"
      },
      {
        "link_thumb": "https://live.staticflickr.com/65535/51808357132_f8c815ffd1_n.jpg",
        "link_img": "https://live.staticflickr.com/65535/51808357132_64bba5a020_o.png",
        "id_image": "evolution_5660272"
      }
    ],
    "hash_code_list_img": "-522684519"
  },
  {
    "link_it": "https://github.com/lmbstudiocontact/cb_img_2500_it_1/raw/main/letter_cb_img_2500_it.json",
    "id_item": "letter_cb_img_2500_it",
    "id_album": "570943428",
    "english": "letter",
    "list_mean": [
      "chữ cái",
      "thư"
    ],
    "cau_en": "",
    "cau_vn": "",
    "hash_code_list_mean": "1959418568",
    "list_img": [
      {
        "link_thumb": "https://live.staticflickr.com/65535/51809459868_9ec2bf2449_n.jpg",
        "link_img": "https://live.staticflickr.com/65535/51809459868_3b760775d5_o.png",
        "id_image": "letter_2300624"
      },
      {
        "link_thumb": "https://live.staticflickr.com/65535/51808390077_1eede0a7a8_n.jpg",
        "link_img": "https://live.staticflickr.com/65535/51808390077_d3c44509cd_o.png",
        "id_image": "letter_547041"
      },
      {
        "link_thumb": "https://live.staticflickr.com/65535/51808390042_f6218399f2_n.jpg",
        "link_img": "https://live.staticflickr.com/65535/51808390042_8d6c8268d3_o.png",
        "id_image": "letter_870121"
      }
    ],
    "hash_code_list_img": "1114443623"
  },
  {
    "link_it": "https://github.com/lmbstudiocontact/cb_img_2500_it_2/raw/main/still_cb_img_2500_it.json",
    "id_item": "still_cb_img_2500_it",
    "id_album": "570943428",
    "english": "still",
    "list_mean": [
      "đứng yên, phẳng lặng",
      "không có ga, không sủi bọt",
      "bức ảnh về một cảnh của bộ phim",
      "vẫn còn",
      "mặc dù vậy, tuy nhiên",
      "thậm chí"
    ],
    "cau_en": "",
    "cau_vn": "",
    "hash_code_list_mean": "1166004776",
    "list_img": [
      {
        "link_thumb": "https://live.staticflickr.com/65535/51809461258_51b8e8c35d_n.jpg",
        "link_img": "https://live.staticflickr.com/65535/51809461258_6fc5d356f5_o.png",
        "id_image": "still_1484373"
      }
    ],
    "hash_code_list_img": "1413295890"
  },
  {
    "link_it": "https://github.com/lmbstudiocontact/cb_img_2500_it_0/raw/main/disposal_cb_img_2500_it.json",
    "id_item": "disposal_cb_img_2500_it",
    "id_album": "570943428",
    "english": "disposal",
    "list_mean": [
      "hành động vứt bỏ cái gì"
    ],
    "cau_en": "",
    "cau_vn": "",
    "hash_code_list_mean": "-2092508420",
    "list_img": [
      {
        "link_thumb": "https://live.staticflickr.com/65535/51808359252_44e8238885_n.jpg",
        "link_img": "https://live.staticflickr.com/65535/51808359252_8a5edc40ee_o.png",
        "id_image": "disposal_2911660"
      },
      {
        "link_thumb": "https://live.staticflickr.com/65535/51810051605_eca663514f_n.jpg",
        "link_img": "https://live.staticflickr.com/65535/51810051605_cb3956da6b_o.png",
        "id_image": "disposal_3154583"
      }
    ],
    "hash_code_list_img": "58587233"
  },
  {
    "link_it": "https://github.com/lmbstudiocontact/cb_img_2500_it_1/raw/main/produce_cb_img_2500_it.json",
    "id_item": "produce_cb_img_2500_it",
    "id_album": "570943428",
    "english": "produce",
    "list_mean": [
      "đưa ra",
      "sinh đẻ",
      "gây ra",
      "sản xuất",
      "cung cấp",
      "dàn dựng",
      "sản phẩm"
    ],
    "cau_en": "",
    "cau_vn": "",
    "hash_code_list_mean": "-712523144",
    "list_img": [
      {
        "link_thumb": "https://live.staticflickr.com/65535/51809437708_fc42dcdd36_n.jpg",
        "link_img": "https://live.staticflickr.com/65535/51809437708_afa162d0bd_o.png",
        "id_image": "produce_1659483"
      },
      {
        "link_thumb": "https://live.staticflickr.com/65535/51809322411_358452cc46_n.jpg",
        "link_img": "https://live.staticflickr.com/65535/51809322411_70c15b0ed4_o.png",
        "id_image": "produce_3967358"
      }
    ],
    "hash_code_list_img": "2034116031"
  },
  {
    "link_it": "https://github.com/lmbstudiocontact/cb_img_2500_it_1/raw/main/meet_cb_img_2500_it.json",
    "id_item": "meet_cb_img_2500_it",
    "id_album": "570943428",
    "english": "meet",
    "list_mean": [
      "gặp gỡ",
      "họp",
      "giới thiệu",
      "giao nhau",
      "đáp ứng",
      "hiện ra",
      "đối mặt",
      "cam chịu",
      "tiếp nhận",
      "cuộc thi đấu"
    ],
    "cau_en": "",
    "cau_vn": "",
    "hash_code_list_mean": "-744015508",
    "list_img": [
      {
        "link_thumb": "https://live.staticflickr.com/65535/51809463388_2e05d902ac_n.jpg",
        "link_img": "https://live.staticflickr.com/65535/51809463388_ed6254dae4_o.png",
        "id_image": "meet_4458775"
      }
    ],
    "hash_code_list_img": "753662030"
  },
  {
    "link_it": "https://github.com/lmbstudiocontact/cb_img_2500_it_1/raw/main/process_cb_img_2500_it.json",
    "id_item": "process_cb_img_2500_it",
    "id_album": "570943428",
    "english": "process",
    "list_mean": [
      "quá trình",
      "quy trình",
      "xử lý"
    ],
    "cau_en": "",
    "cau_vn": "",
    "hash_code_list_mean": "-1575813693",
    "list_img": [
      {
        "link_thumb": "https://live.staticflickr.com/65535/51809322966_3ba1ec8f83_n.jpg",
        "link_img": "https://live.staticflickr.com/65535/51809322966_c25aa31cb2_o.png",
        "id_image": "process_1605297"
      },
      {
        "link_thumb": "https://live.staticflickr.com/65535/51810059660_d440454894_n.jpg",
        "link_img": "https://live.staticflickr.com/65535/51810059660_3a2bb26719_o.png",
        "id_image": "process_2733478"
      },
      {
        "link_thumb": "https://live.staticflickr.com/65535/51808367937_99aeb397ff_n.jpg",
        "link_img": "https://live.staticflickr.com/65535/51808367937_1af682c5c3_o.png",
        "id_image": "process_296930"
      },
      {
        "link_thumb": "https://live.staticflickr.com/65535/51810059620_03ab6b0d66_n.jpg",
        "link_img": "https://live.staticflickr.com/65535/51810059620_4e82fde26f_o.png",
        "id_image": "process_4391691"
      },
      {
        "link_thumb": "https://live.staticflickr.com/65535/51809678124_615cb71425_n.jpg",
        "link_img": "https://live.staticflickr.com/65535/51809678124_ac92270bff_o.png",
        "id_image": "process_860483"
      }
    ],
    "hash_code_list_img": "-675487088"
  },
  {
    "link_it": "https://github.com/lmbstudiocontact/cb_img_2500_it_2/raw/main/rotten_cb_img_2500_it.json",
    "id_item": "rotten_cb_img_2500_it",
    "id_album": "570943428",
    "english": "rotten",
    "list_mean": [
      "thiu; ươn",
      "tồi tệ"
    ],
    "cau_en": "",
    "cau_vn": "",
    "hash_code_list_mean": "-1788524686",
    "list_img": [
      {
        "link_thumb": "https://live.staticflickr.com/65535/51810078905_ee1f1d151b_n.jpg",
        "link_img": "https://live.staticflickr.com/65535/51810078905_f2e42d3d24_o.png",
        "id_image": "rotten_4172831"
      },
      {
        "link_thumb": "https://live.staticflickr.com/65535/51808386512_3c8143c99f_n.jpg",
        "link_img": "https://live.staticflickr.com/65535/51808386512_1ca6227528_o.png",
        "id_image": "rotten_5256354"
      },
      {
        "link_thumb": "https://live.staticflickr.com/65535/51808386487_81d6115958_n.jpg",
        "link_img": "https://live.staticflickr.com/65535/51808386487_34c7076fd6_o.png",
        "id_image": "rotten_5671101"
      }
    ],
    "hash_code_list_img": "-1103364526"
  },
  {
    "link_it": "https://github.com/lmbstudiocontact/cb_img_2500_it_1/raw/main/male_cb_img_2500_it.json",
    "id_item": "male_cb_img_2500_it",
    "id_album": "570943428",
    "english": "male",
    "list_mean": [
      "đàn ông; đực; trống",
      "nhị hoa"
    ],
    "cau_en": "",
    "cau_vn": "",
    "hash_code_list_mean": "663989687",
    "list_img": [
      {
        "link_thumb": "https://live.staticflickr.com/65535/51809442983_15f0fa00c0_n.jpg",
        "link_img": "https://live.staticflickr.com/65535/51809442983_4540f0dc60_o.png",
        "id_image": "male_5983706"
      },
      {
        "link_thumb": "https://live.staticflickr.com/65535/51810064585_fd7d107938_n.jpg",
        "link_img": "https://live.staticflickr.com/65535/51810064585_84965c2d93_o.png",
        "id_image": "male_6314150"
      }
    ],
    "hash_code_list_img": "561931975"
  },
  {
    "link_it": "https://github.com/lmbstudiocontact/cb_img_2500_it_1/raw/main/marine_cb_img_2500_it.json",
    "id_item": "marine_cb_img_2500_it",
    "id_album": "570943428",
    "english": "marine",
    "list_mean": [
      "thuộc biển",
      "hải quân"
    ],
    "cau_en": "",
    "cau_vn": "",
    "hash_code_list_mean": "766749500",
    "list_img": [
      {
        "link_thumb": "https://live.staticflickr.com/65535/51809678529_d6ce00a9b1_n.jpg",
        "link_img": "https://live.staticflickr.com/65535/51809678529_c65a4529ba_o.png",
        "id_image": "marine_2614598"
      },
      {
        "link_thumb": "https://live.staticflickr.com/65535/51808368202_58c6cfdc90_n.jpg",
        "link_img": "https://live.staticflickr.com/65535/51808368202_c5388f1829_o.png",
        "id_image": "marine_4695130"
      },
      {
        "link_thumb": "https://live.staticflickr.com/65535/51809323261_5175a62c66_n.jpg",
        "link_img": "https://live.staticflickr.com/65535/51809323261_48b0835074_o.png",
        "id_image": "marine_5426840"
      },
      {
        "link_thumb": "https://live.staticflickr.com/65535/51808368122_88c1ea5440_n.jpg",
        "link_img": "https://live.staticflickr.com/65535/51808368122_f80c10c648_o.png",
        "id_image": "marine_5969101"
      }
    ],
    "hash_code_list_img": "1596648800"
  },
  {
    "link_it": "https://github.com/lmbstudiocontact/cb_img_2500_it_2/raw/main/wrench_cb_img_2500_it.json",
    "id_item": "wrench_cb_img_2500_it",
    "id_album": "570943428",
    "english": "wrench",
    "list_mean": [
      "giật mạnh",
      "trật khớp",
      "sự giật mạnh",
      "chìa vặn"
    ],
    "cau_en": "",
    "cau_vn": "",
    "hash_code_list_mean": "-851929939",
    "list_img": [
      {
        "link_thumb": "https://live.staticflickr.com/65535/51808377612_29ffa0bf71_n.jpg",
        "link_img": "https://live.staticflickr.com/65535/51808377612_310364248e_o.png",
        "id_image": "wrench_1768196"
      },
      {
        "link_thumb": "https://live.staticflickr.com/65535/51809447813_d40b5ff458_n.jpg",
        "link_img": "https://live.staticflickr.com/65535/51809447813_0826f5412e_o.png",
        "id_image": "wrench_2137963"
      }
    ],
    "hash_code_list_img": "2030719960"
  },
  {
    "link_it": "https://github.com/lmbstudiocontact/cb_img_2500_it_2/raw/main/refuse_cb_img_2500_it.json",
    "id_item": "refuse_cb_img_2500_it",
    "id_album": "570943428",
    "english": "refuse",
    "list_mean": [
      "từ chối",
      "khước từ",
      "không cho phép",
      "đồ thừa"
    ],
    "cau_en": "",
    "cau_vn": "",
    "hash_code_list_mean": "1357363866",
    "list_img": [
      {
        "link_thumb": "https://live.staticflickr.com/65535/51809685179_7b31e8fba0_n.jpg",
        "link_img": "https://live.staticflickr.com/65535/51809685179_014187f50a_o.png",
        "id_image": "refuse_4633904"
      },
      {
        "link_thumb": "https://live.staticflickr.com/65535/51809330111_b766134ca7_n.jpg",
        "link_img": "https://live.staticflickr.com/65535/51809330111_840b6f6a4a_o.png",
        "id_image": "refuse_4633912"
      }
    ],
    "hash_code_list_img": "1062758253"
  },
  {
    "link_it": "https://github.com/lmbstudiocontact/cb_img_2500_it_0/raw/main/fast_cb_img_2500_it.json",
    "id_item": "fast_cb_img_2500_it",
    "id_album": "570943428",
    "english": "fast",
    "list_mean": [
      "nhanh",
      "(đồng hồ) chạy nhanh",
      "vững vàng; chắc chắn",
      "ăn chay; nhịn đói",
      "thời kỳ nhịn ăn, ăn chay, ăn kiêng",
      "bền; không phai",
      "chắc chắn"
    ],
    "cau_en": "",
    "cau_vn": "",
    "hash_code_list_mean": "-1119451344",
    "list_img": [
      {
        "link_thumb": "https://live.staticflickr.com/65535/51810072080_5a6c0fc309_n.jpg",
        "link_img": "https://live.staticflickr.com/65535/51810072080_cbeb096a61_o.png",
        "id_image": "fast_1455324"
      },
      {
        "link_thumb": "https://live.staticflickr.com/65535/51808380177_e2cbef623d_n.jpg",
        "link_img": "https://live.staticflickr.com/65535/51808380177_24f56cac58_o.png",
        "id_image": "fast_1476721"
      },
      {
        "link_thumb": "https://live.staticflickr.com/65535/51809690244_c9dda8eaef_n.jpg",
        "link_img": "https://live.staticflickr.com/65535/51809690244_b38094891c_o.png",
        "id_image": "fast_1652556"
      },
      {
        "link_thumb": "https://live.staticflickr.com/65535/51809690209_0288de1ac8_n.jpg",
        "link_img": "https://live.staticflickr.com/65535/51809690209_37a9f39db9_o.png",
        "id_image": "fast_3043536"
      },
      {
        "link_thumb": "https://live.staticflickr.com/65535/51809335006_9b8fa8c83f_n.jpg",
        "link_img": "https://live.staticflickr.com/65535/51809335006_d97ed4de7a_o.png",
        "id_image": "fast_6316099"
      }
    ],
    "hash_code_list_img": "-1105181557"
  },
  {
    "link_it": "https://github.com/lmbstudiocontact/cb_img_2500_it_0/raw/main/balance_cb_img_2500_it.json",
    "id_item": "balance_cb_img_2500_it",
    "id_album": "570943428",
    "english": "balance",
    "list_mean": [
      "sự thăng bằng",
      "số dư",
      "cái cân",
      "sự cân bằng",
      "làm cho cân bằng",
      "giữ thăng bằng"
    ],
    "cau_en": "",
    "cau_vn": "",
    "hash_code_list_mean": "1295164491",
    "list_img": [
      {
        "link_thumb": "https://live.staticflickr.com/65535/51809319001_3f41685ba1_n.jpg",
        "link_img": "https://live.staticflickr.com/65535/51809319001_093a3ef03c_o.png",
        "id_image": "balance_1656927"
      },
      {
        "link_thumb": "https://live.staticflickr.com/65535/51808363537_70efbac829_n.jpg",
        "link_img": "https://live.staticflickr.com/65535/51808363537_9ae896ff67_o.png",
        "id_image": "balance_1721446"
      },
      {
        "link_thumb": "https://live.staticflickr.com/65535/51809673774_2091cef739_n.jpg",
        "link_img": "https://live.staticflickr.com/65535/51809673774_621d97c9cd_o.png",
        "id_image": "balance_1751694"
      },
      {
        "link_thumb": "https://live.staticflickr.com/65535/51809434243_dc51d8a6af_n.jpg",
        "link_img": "https://live.staticflickr.com/65535/51809434243_7c3843c15e_o.png",
        "id_image": "balance_855370"
      }
    ],
    "hash_code_list_img": "-1450236690"
  },
  {
    "link_it": "https://github.com/lmbstudiocontact/cb_img_2500_it_1/raw/main/lamp_cb_img_2500_it.json",
    "id_item": "lamp_cb_img_2500_it",
    "id_album": "570943428",
    "english": "lamp",
    "list_mean": [
      "bóng đèn"
    ],
    "cau_en": "",
    "cau_vn": "",
    "hash_code_list_mean": "-1137664352",
    "list_img": [
      {
        "link_thumb": "https://live.staticflickr.com/65535/51808367072_8c3233a6a7_n.jpg",
        "link_img": "https://live.staticflickr.com/65535/51808367072_00b31f6135_o.png",
        "id_image": "lamp_1108652"
      },
      {
        "link_thumb": "https://live.staticflickr.com/65535/51809437503_7b24c3dbac_n.jpg",
        "link_img": "https://live.staticflickr.com/65535/51809437503_30034d307f_o.png",
        "id_image": "lamp_164353"
      },
      {
        "link_thumb": "https://live.staticflickr.com/65535/51810059015_bb1067f831_n.jpg",
        "link_img": "https://live.staticflickr.com/65535/51810059015_a7779ab184_o.png",
        "id_image": "lamp_168635"
      },
      {
        "link_thumb": "https://live.staticflickr.com/65535/51809437438_25b6d89575_n.jpg",
        "link_img": "https://live.staticflickr.com/65535/51809437438_df172a622b_o.png",
        "id_image": "lamp_292025"
      }
    ],
    "hash_code_list_img": "1604047356"
  },
  {
    "link_it": "https://github.com/lmbstudiocontact/cb_img_2500_it_2/raw/main/save_cb_img_2500_it.json",
    "id_item": "save_cb_img_2500_it",
    "id_album": "570943428",
    "english": "save",
    "list_mean": [
      "cứu nguy",
      "để dành, tiết kiệm",
      "tránh, bớt",
      "ngăn cản đối phương",
      "cứu rỗi",
      "bảo lưu",
      "sự phá bóng cứu nguy",
      "trừ ra , ngoài ra"
    ],
    "cau_en": "",
    "cau_vn": "",
    "hash_code_list_mean": "1616260053",
    "list_img": [
      {
        "link_thumb": "https://live.staticflickr.com/65535/51808378467_aa56ef73fb_n.jpg",
        "link_img": "https://live.staticflickr.com/65535/51808378467_d5e5048314_o.png",
        "id_image": "save_2997223"
      },
      {
        "link_thumb": "https://live.staticflickr.com/65535/51808378552_360636c83f_n.jpg",
        "link_img": "https://live.staticflickr.com/65535/51808378552_be68768f8b_o.png",
        "id_image": "save_333777"
      },
      {
        "link_thumb": "https://live.staticflickr.com/65535/51808378507_be36b7dc84_n.jpg",
        "link_img": "https://live.staticflickr.com/65535/51808378507_cde0ece95c_o.png",
        "id_image": "save_364146"
      }
    ],
    "hash_code_list_img": "431859821"
  },
  {
    "link_it": "https://github.com/lmbstudiocontact/cb_img_2500_it_2/raw/main/silver_cb_img_2500_it.json",
    "id_item": "silver_cb_img_2500_it",
    "id_album": "570943428",
    "english": "silver",
    "list_mean": [
      "bạc",
      "đồ dùng bằng bạc",
      "làm bằng bạc, trông như bạc",
      "thứ hai mươi lăm"
    ],
    "cau_en": "",
    "cau_vn": "",
    "hash_code_list_mean": "1169085783",
    "list_img": [
      {
        "link_thumb": "https://live.staticflickr.com/65535/51809338431_30c4d39b5d_n.jpg",
        "link_img": "https://live.staticflickr.com/65535/51809338431_f2894d9e04_o.png",
        "id_image": "silver_1176235"
      },
      {
        "link_thumb": "https://live.staticflickr.com/65535/51809693594_9739ed1b28_n.jpg",
        "link_img": "https://live.staticflickr.com/65535/51809693594_49077472c1_o.png",
        "id_image": "silver_4033743"
      }
    ],
    "hash_code_list_img": "-301124359"
  },
  {
    "link_it": "https://github.com/lmbstudiocontact/cb_img_2500_it_2/raw/main/stubborn_cb_img_2500_it.json",
    "id_item": "stubborn_cb_img_2500_it",
    "id_album": "570943428",
    "english": "stubborn",
    "list_mean": [
      "bướng bỉnh, ngoan cố"
    ],
    "cau_en": "",
    "cau_vn": "",
    "hash_code_list_mean": "-1205073831",
    "list_img": [
      {
        "link_thumb": "https://live.staticflickr.com/65535/51808386632_98fcb24e25_n.jpg",
        "link_img": "https://live.staticflickr.com/65535/51808386632_dd8d6b710f_o.png",
        "id_image": "stubborn_3362372"
      }
    ],
    "hash_code_list_img": "532299765"
  },
  {
    "link_it": "https://github.com/lmbstudiocontact/cb_img_2500_it_0/raw/main/discord_cb_img_2500_it.json",
    "id_item": "discord_cb_img_2500_it",
    "id_album": "570943428",
    "english": "discord",
    "list_mean": [
      "sự bất hòa",
      "sự không hợp âm"
    ],
    "cau_en": "",
    "cau_vn": "",
    "hash_code_list_mean": "2035903075",
    "list_img": [
      {
        "link_thumb": "https://live.staticflickr.com/65535/51808362087_1740b227c6_n.jpg",
        "link_img": "https://live.staticflickr.com/65535/51808362087_7e47ba98fe_o.png",
        "id_image": "discord_2111310"
      },
      {
        "link_thumb": "https://live.staticflickr.com/65535/51809672459_5f3b37d4eb_n.jpg",
        "link_img": "https://live.staticflickr.com/65535/51809672459_fe23cb456d_o.png",
        "id_image": "discord_356060"
      },
      {
        "link_thumb": "https://live.staticflickr.com/65535/51810054200_5d28423466_n.jpg",
        "link_img": "https://live.staticflickr.com/65535/51810054200_1205d174c1_o.png",
        "id_image": "discord_3767306"
      },
      {
        "link_thumb": "https://live.staticflickr.com/65535/51809432773_ce22f99866_n.jpg",
        "link_img": "https://live.staticflickr.com/65535/51809432773_31c7c04160_o.png",
        "id_image": "discord_4053305"
      }
    ],
    "hash_code_list_img": "2082460489"
  },
  {
    "link_it": "https://github.com/lmbstudiocontact/cb_img_2500_it_2/raw/main/shop_cb_img_2500_it.json",
    "id_item": "shop_cb_img_2500_it",
    "id_album": "570943428",
    "english": "shop",
    "list_mean": [
      "cửa hàng",
      "phân xưởng",
      "đi mua hàng ở chợ"
    ],
    "cau_en": "",
    "cau_vn": "",
    "hash_code_list_mean": "951496242",
    "list_img": [
      {
        "link_thumb": "https://live.staticflickr.com/65535/51808388332_2723ddd983_n.jpg",
        "link_img": "https://live.staticflickr.com/65535/51808388332_cae57b45e3_o.png",
        "id_image": "shop_290957"
      },
      {
        "link_thumb": "https://live.staticflickr.com/65535/51810080790_655f2e7a4f_n.jpg",
        "link_img": "https://live.staticflickr.com/65535/51810080790_be83f6b53d_o.png",
        "id_image": "shop_298338"
      },
      {
        "link_thumb": "https://live.staticflickr.com/65535/51809343276_17fba94c33_n.jpg",
        "link_img": "https://live.staticflickr.com/65535/51809343276_acd76458fc_o.png",
        "id_image": "shop_606817"
      }
    ],
    "hash_code_list_img": "1956910717"
  },
  {
    "link_it": "https://github.com/lmbstudiocontact/cb_img_2500_it_2/raw/main/slave_cb_img_2500_it.json",
    "id_item": "slave_cb_img_2500_it",
    "id_album": "570943428",
    "english": "slave",
    "list_mean": [
      "người nô lệ",
      "người làm việc đầu tắt, mặt tối",
      "làm việc quần quật"
    ],
    "cau_en": "",
    "cau_vn": "",
    "hash_code_list_mean": "649099382",
    "list_img": [
      {
        "link_thumb": "https://live.staticflickr.com/65535/51809689619_ed169e66aa_n.jpg",
        "link_img": "https://live.staticflickr.com/65535/51809689619_f78fd7baef_o.png",
        "id_image": "slave_5773048"
      },
      {
        "link_thumb": "https://live.staticflickr.com/65535/51809689574_248c171dde_n.jpg",
        "link_img": "https://live.staticflickr.com/65535/51809689574_8a5ae9b923_o.png",
        "id_image": "slave_5906183"
      },
      {
        "link_thumb": "https://live.staticflickr.com/65535/51808379397_46685ef08a_n.jpg",
        "link_img": "https://live.staticflickr.com/65535/51808379397_a59ea76cdb_o.png",
        "id_image": "slave_6146655"
      }
    ],
    "hash_code_list_img": "-2083061126"
  },
  {
    "link_it": "https://github.com/lmbstudiocontact/cb_img_2500_it_1/raw/main/patchwork_cb_img_2500_it.json",
    "id_item": "patchwork_cb_img_2500_it",
    "id_album": "570943428",
    "english": "patchwork",
    "list_mean": [
      "miếng vải chắp vá"
    ],
    "cau_en": "",
    "cau_vn": "",
    "hash_code_list_mean": "54924124",
    "list_img": [
      {
        "link_thumb": "https://live.staticflickr.com/65535/51809683624_d823ba6cc2_n.jpg",
        "link_img": "https://live.staticflickr.com/65535/51809683624_d537fdbc7c_o.png",
        "id_image": "patchwork_2133960"
      },
      {
        "link_thumb": "https://live.staticflickr.com/65535/51808373227_4cdceaef91_n.jpg",
        "link_img": "https://live.staticflickr.com/65535/51808373227_d8ed82b4d2_o.png",
        "id_image": "patchwork_6306788"
      }
    ],
    "hash_code_list_img": "1962366246"
  },
  {
    "link_it": "https://github.com/lmbstudiocontact/cb_img_2500_it_0/raw/main/consignment_cb_img_2500_it.json",
    "id_item": "consignment_cb_img_2500_it",
    "id_album": "570943428",
    "english": "consignment",
    "list_mean": [
      "sự ủy thác"
    ],
    "cau_en": "",
    "cau_vn": "",
    "hash_code_list_mean": "-642330399",
    "list_img": [
      {
        "link_thumb": "https://live.staticflickr.com/65535/51809665199_84034715ed_n.jpg",
        "link_img": "https://live.staticflickr.com/65535/51809665199_c689cf0f5d_o.png",
        "id_image": "consignment_2463819"
      }
    ],
    "hash_code_list_img": "1032575136"
  },
  {
    "link_it": "https://github.com/lmbstudiocontact/cb_img_2500_it_0/raw/main/drug_cb_img_2500_it.json",
    "id_item": "drug_cb_img_2500_it",
    "id_album": "570943428",
    "english": "drug",
    "list_mean": [
      "thuốc",
      "ma túy; thuốc ngủ",
      "dùng ma túy; thuốc ngủ"
    ],
    "cau_en": "",
    "cau_vn": "",
    "hash_code_list_mean": "1999251488",
    "list_img": [
      {
        "link_thumb": "https://live.staticflickr.com/65535/51809692209_9e1df29913_n.jpg",
        "link_img": "https://live.staticflickr.com/65535/51809692209_3f4f4b5514_o.png",
        "id_image": "drug_2843761"
      },
      {
        "link_thumb": "https://live.staticflickr.com/65535/51809692164_f93eb6230d_n.jpg",
        "link_img": "https://live.staticflickr.com/65535/51809692164_4448539324_o.png",
        "id_image": "drug_2861164"
      },
      {
        "link_thumb": "https://live.staticflickr.com/65535/51809692249_29dbd630df_n.jpg",
        "link_img": "https://live.staticflickr.com/65535/51809692249_1a8c92c5ed_o.png",
        "id_image": "drug_452700"
      }
    ],
    "hash_code_list_img": "-2020030048"
  },
  {
    "link_it": "https://github.com/lmbstudiocontact/cb_img_2500_it_1/raw/main/pond_cb_img_2500_it.json",
    "id_item": "pond_cb_img_2500_it",
    "id_album": "570943428",
    "english": "pond",
    "list_mean": [
      "cái ao"
    ],
    "cau_en": "",
    "cau_vn": "",
    "hash_code_list_mean": "-1249727166",
    "list_img": [
      {
        "link_thumb": "https://live.staticflickr.com/65535/51809451148_f7634c80d6_n.jpg",
        "link_img": "https://live.staticflickr.com/65535/51809451148_cf90f91a2d_o.png",
        "id_image": "pond_1312012"
      },
      {
        "link_thumb": "https://live.staticflickr.com/65535/51810073085_31584202e1_n.jpg",
        "link_img": "https://live.staticflickr.com/65535/51810073085_8b4e82dced_o.png",
        "id_image": "pond_3038834"
      },
      {
        "link_thumb": "https://live.staticflickr.com/65535/51809451103_2be50eb8fe_n.jpg",
        "link_img": "https://live.staticflickr.com/65535/51809451103_c1f715251d_o.png",
        "id_image": "pond_4146240"
      },
      {
        "link_thumb": "https://live.staticflickr.com/65535/51809451048_9081db9a6a_n.jpg",
        "link_img": "https://live.staticflickr.com/65535/51809451048_f92a33dc61_o.png",
        "id_image": "pond_4251881"
      }
    ],
    "hash_code_list_img": "-483866055"
  },
  {
    "link_it": "https://github.com/lmbstudiocontact/cb_img_2500_it_1/raw/main/offshore_cb_img_2500_it.json",
    "id_item": "offshore_cb_img_2500_it",
    "id_album": "570943428",
    "english": "offshore",
    "list_mean": [
      "ngoài khơi",
      "khỏi bờ"
    ],
    "cau_en": "",
    "cau_vn": "",
    "hash_code_list_mean": "-508517953",
    "list_img": [
      {
        "link_thumb": "https://live.staticflickr.com/65535/51808392817_46d542f267_n.jpg",
        "link_img": "https://live.staticflickr.com/65535/51808392817_80e0b90ea8_o.png",
        "id_image": "offshore_1486217"
      },
      {
        "link_thumb": "https://live.staticflickr.com/65535/51809347906_d243e3d9d2_n.jpg",
        "link_img": "https://live.staticflickr.com/65535/51809347906_ec31b5cb19_o.png",
        "id_image": "offshore_2321487"
      },
      {
        "link_thumb": "https://live.staticflickr.com/65535/51810085185_41afa433f7_n.jpg",
        "link_img": "https://live.staticflickr.com/65535/51810085185_9b615f3a47_o.png",
        "id_image": "offshore_6315464"
      }
    ],
    "hash_code_list_img": "819100718"
  },
  {
    "link_it": "https://github.com/lmbstudiocontact/cb_img_2500_it_2/raw/main/technology_cb_img_2500_it.json",
    "id_item": "technology_cb_img_2500_it",
    "id_album": "570943428",
    "english": "technology",
    "list_mean": [
      "công nghệ"
    ],
    "cau_en": "",
    "cau_vn": "",
    "hash_code_list_mean": "-977473811",
    "list_img": [
      {
        "link_thumb": "https://live.staticflickr.com/65535/51809467868_963b7b7430_n.jpg",
        "link_img": "https://live.staticflickr.com/65535/51809467868_cce6cf25fc_o.png",
        "id_image": "technology_1610456"
      },
      {
        "link_thumb": "https://live.staticflickr.com/65535/51809467843_9d7f7c24fd_n.jpg",
        "link_img": "https://live.staticflickr.com/65535/51809467843_8fdac96da8_o.png",
        "id_image": "technology_3382619"
      },
      {
        "link_thumb": "https://live.staticflickr.com/65535/51810090540_897419d9fa_n.jpg",
        "link_img": "https://live.staticflickr.com/65535/51810090540_9575513dff_o.png",
        "id_image": "technology_752613"
      }
    ],
    "hash_code_list_img": "327468336"
  },
  {
    "link_it": "https://github.com/lmbstudiocontact/cb_img_2500_it_2/raw/main/verdict_cb_img_2500_it.json",
    "id_item": "verdict_cb_img_2500_it",
    "id_album": "570943428",
    "english": "verdict",
    "list_mean": [
      "lời phán quyết",
      "sự nhận định"
    ],
    "cau_en": "",
    "cau_vn": "",
    "hash_code_list_mean": "-1104688671",
    "list_img": [
      {
        "link_thumb": "https://live.staticflickr.com/65535/51809346441_b150532dd3_n.jpg",
        "link_img": "https://live.staticflickr.com/65535/51809346441_b6c6661fb0_o.png",
        "id_image": "verdict_2861325"
      }
    ],
    "hash_code_list_img": "542306484"
  },
  {
    "link_it": "https://github.com/lmbstudiocontact/cb_img_2500_it_1/raw/main/ornament_cb_img_2500_it.json",
    "id_item": "ornament_cb_img_2500_it",
    "id_album": "570943428",
    "english": "ornament",
    "list_mean": [
      "đồ trang trí",
      "trang trí"
    ],
    "cau_en": "",
    "cau_vn": "",
    "hash_code_list_mean": "-573632481",
    "list_img": [
      {
        "link_thumb": "https://live.staticflickr.com/65535/51810080310_0fecd2755c_n.jpg",
        "link_img": "https://live.staticflickr.com/65535/51810080310_c60f995170_o.png",
        "id_image": "ornament_1172850"
      },
      {
        "link_thumb": "https://live.staticflickr.com/65535/51810080270_e098a3ca31_n.jpg",
        "link_img": "https://live.staticflickr.com/65535/51810080270_73d31f6fac_o.png",
        "id_image": "ornament_5493046"
      },
      {
        "link_thumb": "https://live.staticflickr.com/65535/51809342791_3019842c87_n.jpg",
        "link_img": "https://live.staticflickr.com/65535/51809342791_5e8a9bac22_o.png",
        "id_image": "ornament_5830253"
      },
      {
        "link_thumb": "https://live.staticflickr.com/65535/51809342746_77be6e64ed_n.jpg",
        "link_img": "https://live.staticflickr.com/65535/51809342746_3b5275013f_o.png",
        "id_image": "ornament_6240758"
      }
    ],
    "hash_code_list_img": "-1979253175"
  },
  {
    "link_it": "https://github.com/lmbstudiocontact/cb_img_2500_it_0/raw/main/dot_cb_img_2500_it.json",
    "id_item": "dot_cb_img_2500_it",
    "id_album": "570943428",
    "english": "dot",
    "list_mean": [
      "chấm nhỏ"
    ],
    "cau_en": "",
    "cau_vn": "",
    "hash_code_list_mean": "-90242207",
    "list_img": [
      {
        "link_thumb": "https://live.staticflickr.com/65535/51808352687_6f02cf2e97_n.jpg",
        "link_img": "https://live.staticflickr.com/65535/51808352687_21924b5698_o.png",
        "id_image": "dots_2620278"
      },
      {
        "link_thumb": "https://live.staticflickr.com/65535/51810045435_42462a9b66_n.jpg",
        "link_img": "https://live.staticflickr.com/65535/51810045435_2e0aaec2dd_o.png",
        "id_image": "dots_4456810"
      },
      {
        "link_thumb": "https://live.staticflickr.com/65535/51810045615_5c77a517d1_n.jpg",
        "link_img": "https://live.staticflickr.com/65535/51810045615_1ff61dd671_o.png",
        "id_image": "dot_1088797"
      },
      {
        "link_thumb": "https://live.staticflickr.com/65535/51808352772_96a42e052b_n.jpg",
        "link_img": "https://live.staticflickr.com/65535/51808352772_e37ebf4e38_o.png",
        "id_image": "dot_2785319"
      },
      {
        "link_thumb": "https://live.staticflickr.com/65535/51808352752_f51dd976d9_n.jpg",
        "link_img": "https://live.staticflickr.com/65535/51808352752_7346f7c641_o.png",
        "id_image": "dot_5982583"
      }
    ],
    "hash_code_list_img": "454717669"
  },
  {
    "link_it": "https://github.com/lmbstudiocontact/cb_img_2500_it_1/raw/main/jury_cb_img_2500_it.json",
    "id_item": "jury_cb_img_2500_it",
    "id_album": "570943428",
    "english": "jury",
    "list_mean": [
      "Bồi thẩm đoàn",
      "ban giám khảo"
    ],
    "cau_en": "",
    "cau_vn": "",
    "hash_code_list_mean": "-647940705",
    "list_img": [
      {
        "link_thumb": "https://live.staticflickr.com/65535/51809685289_5da47ef0f8_n.jpg",
        "link_img": "https://live.staticflickr.com/65535/51809685289_3517035b47_o.png",
        "id_image": "jury_1284697"
      },
      {
        "link_thumb": "https://live.staticflickr.com/65535/51809445173_67eed6f35b_n.jpg",
        "link_img": "https://live.staticflickr.com/65535/51809445173_5d92c77c6a_o.png",
        "id_image": "jury_1865618"
      },
      {
        "link_thumb": "https://live.staticflickr.com/65535/51809685229_26028003e5_n.jpg",
        "link_img": "https://live.staticflickr.com/65535/51809685229_37c1f849a0_o.png",
        "id_image": "jury_2861271"
      },
      {
        "link_thumb": "https://live.staticflickr.com/65535/51810067130_f632c18ed8_n.jpg",
        "link_img": "https://live.staticflickr.com/65535/51810067130_ed3ceb3ba9_o.png",
        "id_image": "jury_372308"
      },
      {
        "link_thumb": "https://live.staticflickr.com/65535/51808374827_0f9bf41d2a_n.jpg",
        "link_img": "https://live.staticflickr.com/65535/51808374827_bd0cef7900_o.png",
        "id_image": "jury_4391491"
      }
    ],
    "hash_code_list_img": "1525453237"
  },
  {
    "link_it": "https://github.com/lmbstudiocontact/cb_img_2500_it_2/raw/main/unite_cb_img_2500_it.json",
    "id_item": "unite_cb_img_2500_it",
    "id_album": "570943428",
    "english": "unite",
    "list_mean": [
      "hợp nhất",
      "đoàn kết"
    ],
    "cau_en": "",
    "cau_vn": "",
    "hash_code_list_mean": "1494451801",
    "list_img": [
      {
        "link_thumb": "https://live.staticflickr.com/65535/51809707419_5ffe539df0_n.jpg",
        "link_img": "https://live.staticflickr.com/65535/51809707419_072e26a491_o.png",
        "id_image": "unite_232954"
      },
      {
        "link_thumb": "https://live.staticflickr.com/65535/51809707384_aaf6089474_n.jpg",
        "link_img": "https://live.staticflickr.com/65535/51809707384_25b15ee093_o.png",
        "id_image": "unite_2844578"
      },
      {
        "link_thumb": "https://live.staticflickr.com/65535/51809707364_3a47224953_n.jpg",
        "link_img": "https://live.staticflickr.com/65535/51809707364_c6a43300c2_o.png",
        "id_image": "unite_5376888"
      }
    ],
    "hash_code_list_img": "-1255895759"
  },
  {
    "link_it": "https://github.com/lmbstudiocontact/cb_img_2500_it_0/raw/main/box_cb_img_2500_it.json",
    "id_item": "box_cb_img_2500_it",
    "id_album": "570943428",
    "english": "box",
    "list_mean": [
      "hộp; thùng",
      "lô (rạp hát)",
      "bỏ vào hộp",
      "đấm",
      "cái bạt tai"
    ],
    "cau_en": "",
    "cau_vn": "",
    "hash_code_list_mean": "2098911920",
    "list_img": [
      {
        "link_thumb": "https://live.staticflickr.com/65535/51809675039_e15cf3628b_n.jpg",
        "link_img": "https://live.staticflickr.com/65535/51809675039_8eb2c2a3fc_o.png",
        "id_image": "box_258500"
      },
      {
        "link_thumb": "https://live.staticflickr.com/65535/51809675029_7ea3a680c6_n.jpg",
        "link_img": "https://live.staticflickr.com/65535/51809675029_a7b13e7a0b_o.png",
        "id_image": "box_337150"
      },
      {
        "link_thumb": "https://live.staticflickr.com/65535/51809435148_becbd98dc5_n.jpg",
        "link_img": "https://live.staticflickr.com/65535/51809435148_5b3dd848ae_o.png",
        "id_image": "box_588424"
      }
    ],
    "hash_code_list_img": "-1755548461"
  },
  {
    "link_it": "https://github.com/lmbstudiocontact/cb_img_2500_it_2/raw/main/venom_cb_img_2500_it.json",
    "id_item": "venom_cb_img_2500_it",
    "id_album": "570943428",
    "english": "venom",
    "list_mean": [
      "nọc độc",
      "sự căm ghét"
    ],
    "cau_en": "",
    "cau_vn": "",
    "hash_code_list_mean": "307773251",
    "list_img": [
      {
        "link_thumb": "https://live.staticflickr.com/65535/51808391722_bc3f4c337b_n.jpg",
        "link_img": "https://live.staticflickr.com/65535/51808391722_5bdaba079b_o.png",
        "id_image": "venom_5671603"
      }
    ],
    "hash_code_list_img": "909315079"
  },
  {
    "link_it": "https://github.com/lmbstudiocontact/cb_img_2500_it_1/raw/main/moon_cb_img_2500_it.json",
    "id_item": "moon_cb_img_2500_it",
    "id_album": "570943428",
    "english": "moon",
    "list_mean": [
      "mặt trăng",
      "vệ tinh"
    ],
    "cau_en": "",
    "cau_vn": "",
    "hash_code_list_mean": "1774321783",
    "list_img": [
      {
        "link_thumb": "https://live.staticflickr.com/65535/51810073810_7daf68106f_n.jpg",
        "link_img": "https://live.staticflickr.com/65535/51810073810_a6e17ac590_o.png",
        "id_image": "moon_167317"
      },
      {
        "link_thumb": "https://live.staticflickr.com/65535/51810073770_20b4c80fee_n.jpg",
        "link_img": "https://live.staticflickr.com/65535/51810073770_9958765725_o.png",
        "id_image": "moon_178534"
      },
      {
        "link_thumb": "https://live.staticflickr.com/65535/51809692014_fb4eedb2c8_n.jpg",
        "link_img": "https://live.staticflickr.com/65535/51809692014_d31425abdf_o.png",
        "id_image": "moon_433842"
      }
    ],
    "hash_code_list_img": "578131622"
  },
  {
    "link_it": "https://github.com/lmbstudiocontact/cb_img_2500_it_2/raw/main/ray_cb_img_2500_it.json",
    "id_item": "ray_cb_img_2500_it",
    "id_album": "570943428",
    "english": "ray",
    "list_mean": [
      "tia",
      "chút ít"
    ],
    "cau_en": "",
    "cau_vn": "",
    "hash_code_list_mean": "883917757",
    "list_img": [
      {
        "link_thumb": "https://live.staticflickr.com/65535/51808382372_61decd2e92_n.jpg",
        "link_img": "https://live.staticflickr.com/65535/51808382372_0db53fe914_o.png",
        "id_image": "ray_1620443"
      },
      {
        "link_thumb": "https://live.staticflickr.com/65535/51809692644_8e4611edc6_n.jpg",
        "link_img": "https://live.staticflickr.com/65535/51809692644_782f4dd820_o.png",
        "id_image": "ray_1970229"
      },
      {
        "link_thumb": "https://live.staticflickr.com/65535/51808382322_47085aa4fc_n.jpg",
        "link_img": "https://live.staticflickr.com/65535/51808382322_de8d05a85f_o.png",
        "id_image": "ray_4717864"
      }
    ],
    "hash_code_list_img": "-492569459"
  },
  {
    "link_it": "https://github.com/lmbstudiocontact/cb_img_2500_it_0/raw/main/collector_cb_img_2500_it.json",
    "id_item": "collector_cb_img_2500_it",
    "id_album": "570943428",
    "english": "collector",
    "list_mean": [
      "người sưu tầm"
    ],
    "cau_en": "",
    "cau_vn": "",
    "hash_code_list_mean": "-860731916",
    "list_img": [
      {
        "link_thumb": "https://live.staticflickr.com/65535/51809436883_2a3febed09_n.jpg",
        "link_img": "https://live.staticflickr.com/65535/51809436883_e6f948486f_o.png",
        "id_image": "collector_6295456"
      }
    ],
    "hash_code_list_img": "1292599284"
  },
  {
    "link_it": "https://github.com/lmbstudiocontact/cb_img_2500_it_0/raw/main/editor_cb_img_2500_it.json",
    "id_item": "editor_cb_img_2500_it",
    "id_album": "570943428",
    "english": "editor",
    "list_mean": [
      "biên tập viên",
      "người chịu trách nhiệm một phần của tờ báo"
    ],
    "cau_en": "",
    "cau_vn": "",
    "hash_code_list_mean": "-752520870",
    "list_img": [
      {
        "link_thumb": "https://live.staticflickr.com/65535/51810066300_a832d50f0f_n.jpg",
        "link_img": "https://live.staticflickr.com/65535/51810066300_81fa7ecc30_o.png",
        "id_image": "editor_1188482"
      },
      {
        "link_thumb": "https://live.staticflickr.com/65535/51809444478_dfd1f3db89_n.jpg",
        "link_img": "https://live.staticflickr.com/65535/51809444478_97af66e656_o.png",
        "id_image": "editor_1899340"
      },
      {
        "link_thumb": "https://live.staticflickr.com/65535/51809684434_e8bda49c74_n.jpg",
        "link_img": "https://live.staticflickr.com/65535/51809684434_7f0af3c983_o.png",
        "id_image": "editor_3966346"
      },
      {
        "link_thumb": "https://live.staticflickr.com/65535/51808374087_084e17e981_n.jpg",
        "link_img": "https://live.staticflickr.com/65535/51808374087_88be80c03a_o.png",
        "id_image": "editor_4695764"
      }
    ],
    "hash_code_list_img": "-524315175"
  },
  {
    "link_it": "https://github.com/lmbstudiocontact/cb_img_2500_it_1/raw/main/purchase_cb_img_2500_it.json",
    "id_item": "purchase_cb_img_2500_it",
    "id_album": "570943428",
    "english": "purchase",
    "list_mean": [
      "mua",
      "hàng đã mua",
      "sự mua sắm"
    ],
    "cau_en": "",
    "cau_vn": "",
    "hash_code_list_mean": "-1640091674",
    "list_img": [
      {
        "link_thumb": "https://live.staticflickr.com/65535/51809347231_21cf98f58f_n.jpg",
        "link_img": "https://live.staticflickr.com/65535/51809347231_76e507a040_o.png",
        "id_image": "purchase_1198278"
      },
      {
        "link_thumb": "https://live.staticflickr.com/65535/51809702044_77d209a8f0_n.jpg",
        "link_img": "https://live.staticflickr.com/65535/51809702044_3d03c0d8f1_o.png",
        "id_image": "purchase_1648812"
      },
      {
        "link_thumb": "https://live.staticflickr.com/65535/51809702019_33b658c3e0_n.jpg",
        "link_img": "https://live.staticflickr.com/65535/51809702019_bc60d417b4_o.png",
        "id_image": "purchase_4646890"
      },
      {
        "link_thumb": "https://live.staticflickr.com/65535/51810084595_8cb3f6358c_n.jpg",
        "link_img": "https://live.staticflickr.com/65535/51810084595_9253572d31_o.png",
        "id_image": "purchase_5986569"
      }
    ],
    "hash_code_list_img": "-1895539334"
  },
  {
    "link_it": "https://github.com/lmbstudiocontact/cb_img_2500_it_0/raw/main/country_cb_img_2500_it.json",
    "id_item": "country_cb_img_2500_it",
    "id_album": "570943428",
    "english": "country",
    "list_mean": [
      "đất nước",
      "nhân dân",
      "nông thôn",
      "địa hạt"
    ],
    "cau_en": "",
    "cau_vn": "",
    "hash_code_list_mean": "-1670038912",
    "list_img": [
      {
        "link_thumb": "https://live.staticflickr.com/65535/51809682259_3558a0bc9e_n.jpg",
        "link_img": "https://live.staticflickr.com/65535/51809682259_9ea4fb5b96_o.png",
        "id_image": "country_5663672"
      },
      {
        "link_thumb": "https://live.staticflickr.com/65535/51810063955_ebcfe4c099_n.jpg",
        "link_img": "https://live.staticflickr.com/65535/51810063955_74eb0b146c_o.png",
        "id_image": "country_6313937"
      }
    ],
    "hash_code_list_img": "45870101"
  },
  {
    "link_it": "https://github.com/lmbstudiocontact/cb_img_2500_it_2/raw/main/single_cb_img_2500_it.json",
    "id_item": "single_cb_img_2500_it",
    "id_album": "570943428",
    "english": "single",
    "list_mean": [
      "đơn độc",
      "đơn",
      "độc thân",
      "một chiều",
      "đĩa ghi âm mỗi mặt chỉ có ghi một bài hát ngắn",
      "vé một chiều"
    ],
    "cau_en": "",
    "cau_vn": "",
    "hash_code_list_mean": "864013979",
    "list_img": [
      {
        "link_thumb": "https://live.staticflickr.com/65535/51809337656_ef2ca85421_n.jpg",
        "link_img": "https://live.staticflickr.com/65535/51809337656_be498b6563_o.png",
        "id_image": "single_2442287"
      },
      {
        "link_thumb": "https://live.staticflickr.com/65535/51809692899_8920b3a95b_n.jpg",
        "link_img": "https://live.staticflickr.com/65535/51809692899_dcefa8810d_o.png",
        "id_image": "single_5509321"
      }
    ],
    "hash_code_list_img": "-716298137"
  },
  {
    "link_it": "https://github.com/lmbstudiocontact/cb_img_2500_it_1/raw/main/overtake_cb_img_2500_it.json",
    "id_item": "overtake_cb_img_2500_it",
    "id_album": "570943428",
    "english": "overtake",
    "list_mean": [
      "vượt"
    ],
    "cau_en": "",
    "cau_vn": "",
    "hash_code_list_mean": "4175754",
    "list_img": [
      {
        "link_thumb": "https://live.staticflickr.com/65535/51809695189_29a562af10_n.jpg",
        "link_img": "https://live.staticflickr.com/65535/51809695189_42b6fec36c_o.png",
        "id_image": "overtake_2481696"
      },
      {
        "link_thumb": "https://live.staticflickr.com/65535/51810077180_7fc6fc1362_n.jpg",
        "link_img": "https://live.staticflickr.com/65535/51810077180_419b53309b_o.png",
        "id_image": "overtake_4351759"
      },
      {
        "link_thumb": "https://live.staticflickr.com/65535/51808384787_c33a217d21_n.jpg",
        "link_img": "https://live.staticflickr.com/65535/51808384787_265a66ccf8_o.png",
        "id_image": "overtake_4796161"
      }
    ],
    "hash_code_list_img": "753192235"
  },
  {
    "link_it": "https://github.com/lmbstudiocontact/cb_img_2500_it_1/raw/main/hit_cb_img_2500_it.json",
    "id_item": "hit_cb_img_2500_it",
    "id_album": "570943428",
    "english": "hit",
    "list_mean": [
      "đánh, đấm, nện",
      "đâm, đụng",
      "làm tổn thương, làm đau khổ",
      "tìm ra, vớ được",
      "cú đánh; đòn",
      "điểm ghi được",
      "việc thành công"
    ],
    "cau_en": "",
    "cau_vn": "",
    "hash_code_list_mean": "1344248411",
    "list_img": [
      {
        "link_thumb": "https://live.staticflickr.com/65535/51809691254_256b4415aa_n.jpg",
        "link_img": "https://live.staticflickr.com/65535/51809691254_20c473c9bc_o.png",
        "id_image": "hit_1477178"
      }
    ],
    "hash_code_list_img": "1142597581"
  },
  {
    "link_it": "https://github.com/lmbstudiocontact/cb_img_2500_it_1/raw/main/permission_cb_img_2500_it.json",
    "id_item": "permission_cb_img_2500_it",
    "id_album": "570943428",
    "english": "permission",
    "list_mean": [
      "sự cho phép"
    ],
    "cau_en": "",
    "cau_vn": "",
    "hash_code_list_mean": "1756177270",
    "list_img": [
      {
        "link_thumb": "https://live.staticflickr.com/65535/51810057200_8a4f962fff_n.jpg",
        "link_img": "https://live.staticflickr.com/65535/51810057200_6848e2e5e7_o.png",
        "id_image": "permission_2172839"
      },
      {
        "link_thumb": "https://live.staticflickr.com/65535/51808365367_38e9119abd_n.jpg",
        "link_img": "https://live.staticflickr.com/65535/51808365367_471cf897ff_o.png",
        "id_image": "permission_3663412"
      },
      {
        "link_thumb": "https://live.staticflickr.com/65535/51809675384_79814c3e19_n.jpg",
        "link_img": "https://live.staticflickr.com/65535/51809675384_3484555e79_o.png",
        "id_image": "permission_4391723"
      }
    ],
    "hash_code_list_img": "443772453"
  },
  {
    "link_it": "https://github.com/lmbstudiocontact/cb_img_2500_it_0/raw/main/board_cb_img_2500_it.json",
    "id_item": "board_cb_img_2500_it",
    "id_album": "570943428",
    "english": "board",
    "list_mean": [
      "tấm ván",
      "bảng",
      "bàn ăn",
      "ban",
      "lên tàu, xe",
      "ăn ở trọ"
    ],
    "cau_en": "",
    "cau_vn": "",
    "hash_code_list_mean": "-1266949841",
    "list_img": [
      {
        "link_thumb": "https://live.staticflickr.com/65535/51810064015_49c7df2518_n.jpg",
        "link_img": "https://live.staticflickr.com/65535/51810064015_8f6b3be3cd_o.png",
        "id_image": "boards_344061"
      },
      {
        "link_thumb": "https://live.staticflickr.com/65535/51809327236_129e7bfb98_n.jpg",
        "link_img": "https://live.staticflickr.com/65535/51809327236_4d4f84d193_o.png",
        "id_image": "board_4334310"
      },
      {
        "link_thumb": "https://live.staticflickr.com/65535/51809442218_eb337d1666_n.jpg",
        "link_img": "https://live.staticflickr.com/65535/51809442218_539ecf5dd6_o.png",
        "id_image": "board_4371357"
      }
    ],
    "hash_code_list_img": "1263031135"
  },
  {
    "link_it": "https://github.com/lmbstudiocontact/cb_img_2500_it_1/raw/main/profile_cb_img_2500_it.json",
    "id_item": "profile_cb_img_2500_it",
    "id_album": "570943428",
    "english": "profile",
    "list_mean": [
      "nét mặt nhìn nghiêng"
    ],
    "cau_en": "",
    "cau_vn": "",
    "hash_code_list_mean": "643311585",
    "list_img": [
      {
        "link_thumb": "https://live.staticflickr.com/65535/51809676434_73034633f0_n.jpg",
        "link_img": "https://live.staticflickr.com/65535/51809676434_4211f50182_o.png",
        "id_image": "profile_1098778"
      },
      {
        "link_thumb": "https://live.staticflickr.com/65535/51810058100_e084036ce3_n.jpg",
        "link_img": "https://live.staticflickr.com/65535/51810058100_c9775b5334_o.png",
        "id_image": "profile_2058243"
      },
      {
        "link_thumb": "https://live.staticflickr.com/65535/51808366227_bf2390bbf8_n.jpg",
        "link_img": "https://live.staticflickr.com/65535/51808366227_6548fe0dde_o.png",
        "id_image": "profile_4542145"
      }
    ],
    "hash_code_list_img": "-327871384"
  },
  {
    "link_it": "https://github.com/lmbstudiocontact/cb_img_2500_it_1/raw/main/heat_cb_img_2500_it.json",
    "id_item": "heat_cb_img_2500_it",
    "id_album": "570943428",
    "english": "heat",
    "list_mean": [
      "sức nóng",
      "hơi nóng",
      "sự nóng nực",
      "sự hăng hái",
      "đấu loại",
      "nóng lên; trở nên nóng"
    ],
    "cau_en": "",
    "cau_vn": "",
    "hash_code_list_mean": "-1766017960",
    "list_img": [
      {
        "link_thumb": "https://live.staticflickr.com/65535/51809455048_1312ea95c9_n.jpg",
        "link_img": "https://live.staticflickr.com/65535/51809455048_0d344d0997_o.png",
        "id_image": "heat_1870752"
      },
      {
        "link_thumb": "https://live.staticflickr.com/65535/51809340171_476c984c11_n.jpg",
        "link_img": "https://live.staticflickr.com/65535/51809340171_d3ce4c4e6d_o.png",
        "id_image": "heat_3058010"
      },
      {
        "link_thumb": "https://live.staticflickr.com/65535/51810077370_ccd08d5e63_n.jpg",
        "link_img": "https://live.staticflickr.com/65535/51810077370_62ff35267b_o.png",
        "id_image": "heat_6182875"
      }
    ],
    "hash_code_list_img": "1371861365"
  },
  {
    "link_it": "https://github.com/lmbstudiocontact/cb_img_2500_it_0/raw/main/blow_cb_img_2500_it.json",
    "id_item": "blow_cb_img_2500_it",
    "id_album": "570943428",
    "english": "blow",
    "list_mean": [
      "cú đánh",
      "tai hoạ",
      "thổi",
      "cuốn đi",
      "hà hơi vào",
      "thổi (kèn…)"
    ],
    "cau_en": "",
    "cau_vn": "",
    "hash_code_list_mean": "1020871452",
    "list_img": [
      {
        "link_thumb": "https://live.staticflickr.com/65535/51809683639_95b7bfce24_n.jpg",
        "link_img": "https://live.staticflickr.com/65535/51809683639_e093aef47b_o.png",
        "id_image": "blow_1040516"
      },
      {
        "link_thumb": "https://live.staticflickr.com/65535/51809683619_269736533e_n.jpg",
        "link_img": "https://live.staticflickr.com/65535/51809683619_460d757891_o.png",
        "id_image": "blow_4845861"
      }
    ],
    "hash_code_list_img": "-1591927360"
  }
]